{"inkVersion":21,"root":[["\n","\n","\n","\n","\n","\n","\n","\n","\n","\n","\n",["done",{"#f":5,"#n":"g-0"}],null],"done",{"Unity_Event":[{"temp=":"eventName"},"^[ EVENT: ","ev",{"VAR?":"eventName"},"out","/ev","^ ]","\n",{"#f":1}],"Get_State":[{"temp=":"id"},"^[ GET STATE: ","ev",{"VAR?":"id"},"out","/ev","^ ]","\n","ev",0,"/ev","~ret",{"#f":1}],"Add_State":[{"temp=":"amount"},{"temp=":"id"},"^[ ADD STATE: ","ev",{"VAR?":"id"},"out","/ev","^ - VALUE: ","ev",{"VAR?":"amount"},"out","/ev","^ ]","\n",{"#f":1}],"Kevin":[{"->":".^.Start"},{"Start":["ev",{"CNT?":".^.^.Loot"},"/ev",[{"->":".^.b","c":true},{"b":["^ ",{"->":"Kevin.Hub"},{"->":".^.^.^.4"},null]}],"nop","\n","ev",{"CNT?":".^.^.HelfenA"},"/ev",[{"->":".^.b","c":true},{"b":["^ ",{"->":"Kevin.Stahlda"},{"->":".^.^.^.10"},null]}],"nop","\n","ev",{"CNT?":".^.^.Gruss"},"/ev",[{"->":".^.b","c":true},{"b":["^ ",{"->":"Kevin.Versuch2"},{"->":".^.^.^.16"},null]}],"nop","\n",{"->":".^.^.Gruss"},{"#f":1}],"Gruss":[["^Kevin: Sei gegrüsst <color=#66DBFF>Locus</color>! Machet es euch gemütlich in meinem bescheidenen Domizil. ","#","^kevin","/#","\n","^Locus: Danke. Ich hoffe ich störe nicht. ","#","^locus","/#","\n","^Kevin: Nein, ich wollte sowieso eine kurze Pause einlegen. ","#","^kevin","/#","\n","ev","str","^Ich muss ein Fest organisieren","/str",{"CNT?":"Remus.Start"},"/ev",{"*":".^.c-0","flg":21},"ev","str","^An was arbeitest du da?","/str","/ev",{"*":".^.c-1","flg":20},{"c-0":[{"->":"Kevin.Fest"},"\n",{"#f":5}],"c-1":["^ ",{"->":"Kevin.Arbeit"},"\n",{"#f":5}]}],{"#f":1}],"Fest":[["^Locus: Ich muss ein Fest für den <color=#66DBFF>Teufel</color> organisieren. ","#","^locus","/#","\n","^Kevin: Oh, dann wünsche ich dir viel Glück, du weisst ja was mit dem letzten geschah, der diese Aufgabe hatte... ","#","^kevin","/#","\n","ev","str","^Nein, was ist mit ihm?","/str","/ev",{"*":".^.c-0","flg":20},"ev","str","^An was arbeitest du da?","/str",{"CNT?":"Kevin.Arbeit"},"!","/ev",{"*":".^.c-1","flg":21},{"c-0":[{"->":"Kevin.Victus"},"\n",{"#f":5}],"c-1":[{"->":"Kevin.Arbeit"},"\n",{"#f":5}]}],{"#f":1}],"Victus":["^Lovus: Nein, was ist mit ihm? ","#","^locus","/#","\n","^Kevin: Der bedauerliche <color=#66DBFF>Victus</color> hatte zuletzt diese Aufgabe. Doch hatte er zu diesem Fest weder <color=#58FF5E>Teller</color>, <color=#58FF5E>Getränke</color>,","\n","<>","^ <color=#58FF5E>Ballons</color> und schon gar keinen <color=#58FF5E>Kuchen</color> besorgt. ","#","^kevin","/#","\n","^Kevin: Wie du dir vorstellen kannst, war der <color=#66DBFF>Meister</color> nicht sehr erfreut darüber. ","#","^kevin","/#","\n","^Kevin: <color=#66DBFF>Victus</color> wurde daraufhin versetzt. Er muss sich nun um alle Franzosen der Hölle kümmern. ","#","^kevin","/#","\n","^Kevin: Trotzdessen wünsche ich dir nur das Beste. ","#","^kevin","/#","\n","ev",{"CNT?":".^.^.WhyTeller"},"/ev",[{"->":".^.b","c":true},{"b":["^ ",{"->":"Kevin.Hub"},{"->":".^.^.^.32"},null]}],"nop","\n","ev",{"CNT?":".^.^.Hub"},"/ev",[{"->":".^.b","c":true},{"b":["^ ",{"->":"Kevin.Hub"},{"->":".^.^.^.38"},null]}],"nop","\n",{"->":".^.^.Arbeit"},{"#f":1}],"Arbeit":[["^Locus: An was arbeitest du da? ","#","^locus","/#","\n","^Kevin: Ich bin drauf und dran das <color=#58FF5E>Zepter</color> meines Arbeitgebers zu restaurieren, doch stelle ich mit","\n","<>","^ Schrecken fest, dass es mir an <color=#58FF5E>Höllenstahl</color> mangelt. ","#","^kevin","/#","\n","ev","str","^Höllenstahl?","/str","/ev",{"*":".^.c-0","flg":20},"ev","str","^Wie kann ich helfen?","/str","/ev",{"*":".^.c-1","flg":4},"ev","str","^Was geht mich das an?","/str","/ev",{"*":".^.c-2","flg":20},"ev","str","^Gehen","/str","/ev",{"*":".^.c-3","flg":4},{"c-0":[{"->":"Kevin.Stahl"},"\n",{"#f":5}],"c-1":[{"->":"Kevin.Helfen"},"\n",{"#f":5}],"c-2":[{"->":"Kevin.angehen"},"\n",{"#f":5}],"c-3":["^ ",{"->":"Kevin.Gehen1"},"\n",{"#f":5}]}],{"#f":1}],"Stahl":[["^Locus: Was zum Chef ist denn <color=#58FF5E>Höllenstahl</color>? ","#","^locus","/#","\n","^Kevin: Es schmerzt festzustellen, dass du solch mangelndes Verstädnis über grundlegende Praktiken meiner Arbeit hast. ","#","^kevin","/#","\n","^Kevin: Der <color=#58FF5E>Höllenstahl</color> ist eines meiner wichtigesten und rarsten Materialien. Nur der <color=#66DBFF>Meister</color> höchst selbst kann es fertigen. ","#","^kevin","/#","\n","ev","str","^Wie kann ich da helfen?","/str","/ev",{"*":".^.c-0","flg":4},"ev","str","^Gehen","/str","/ev",{"*":".^.c-1","flg":4},{"c-0":["^ ",{"->":"Kevin.Helfen"},"\n",{"#f":5}],"c-1":[{"->":"Kevin.Gehen1"},"\n",{"#f":5}]}],{"#f":1}],"Helfen":[["^Locus: Kann ich dir irgendwie helfen? ","#","^locus","/#","\n","^Kevin: Du möchtest mich in der hohen Kunst des Schmiedens unterstützen? ","#","^kevin","/#","\n","ev","str","^Ja","/str","/ev",{"*":".^.c-0","flg":4},"ev","str","^Nein","/str","/ev",{"*":".^.c-1","flg":4},{"c-0":["^ Locus: Ja, ",{"->":"Kevin.HelfenA"},"\n",{"#f":5}],"c-1":[{"->":"Kevin.HelfenB"},"\n",{"#f":5}]}],{"#f":1}],"angehen":[["^Locus: Was geht mich das an? ","#","^locus","/#","\n","^Kevin: Angesichts dessen, dass du dieses Spiel hier durchspielen möchtest, solltest du dich um nettere","\n","<>","^ Dialogoptionen bemühen! ","#","^kevin","/#","\n","ev","str","^Wie du willst","/str","/ev",{"*":".^.c-0","flg":20},"ev","str","^Das werde ich","/str","/ev",{"*":".^.c-1","flg":20},"ev","str","^Ich liebe dieses Spiel jetzt schon","/str","/ev",{"*":".^.c-2","flg":20},{"c-0":["\n",{"->":".^.^.g-0"},{"#f":5}],"c-1":["\n",{"->":".^.^.g-0"},{"#f":5}],"c-2":["^ ","\n",{"->":".^.^.g-0"},{"#f":5}],"g-0":[{"->":"Kevin.Besserung"},{"#f":5}]}],{"#f":1}],"Besserung":[["^Locus: Ich werde mich bessern. ","#","^locus","/#","\n","^Kevin: Gut, dann will ich mal nicht so sein. Also du wolltest sagen? ","#","^kevin","/#","\n","ev","str","^Was ist Höllenstahl?","/str",{"CNT?":"Kevin.Stahl"},"!","/ev",{"*":".^.c-0","flg":21},"ev","str","^Wie kann ich helfen?","/str","/ev",{"*":".^.c-1","flg":4},"ev","str","^Gehen","/str","/ev",{"*":".^.c-2","flg":4},{"c-0":[{"->":"Kevin.Stahl"},"\n",{"#f":5}],"c-1":["^ ",{"->":"Kevin.Helfen"},"\n",{"#f":5}],"c-2":["^ ",{"->":"Kevin.Gehen1"},"\n",{"#f":5}]}],{"#f":1}],"Gehen1":["^Locus: Ich habe einen Ofen auf meinem Auflauf vergessen! ","#","^locus","/#","\n","^Kevin: Gute Besserung. ","#","^kevin","/#","\n","end",{"#f":1}],"HelfenA":["^ich möchte mich nützlich machen. ","#","^locus","/#","\n","^Kevin: Nun denn, ich denke ich habe da eine kleine Aufgabe für jemanden deines Kalibers. ","#","^kevin","/#","\n","^Kevin: Gehe bitte zu <color=#66DBFF>Remus</color> und bitte ihn um einen Nachschub von einem <color=#58FF5E>Höllenstahlbarren</color>. ","#","^kevin","/#","\n","^Locus: Dann mache ich mich mal auf den Weg. ","#","^locus","/#","\n","ev","str","^Q-Kevin-1","/str",{"x()":"Unity_Event","exArgs":1},"pop","/ev","\n","end",{"#f":1}],"HelfenB":[["^Locus: Nein.","\n","^Kevin: Es scheint mir du beliebst zu scherzen. ","#","^kevin","/#","\n","ev","str","^Ich möchte doch helfen","/str","/ev",{"*":".^.c-0","flg":4},"ev","str","^Gehen","/str","/ev",{"*":".^.c-1","flg":4},{"c-0":["^ Locus: Nagut, ",{"->":"Kevin.HelfenA"},"\n",{"#f":5}],"c-1":["^ Locus: Ich muss meine Zombies füttern. ","#","^locus","/#","\n","end",{"#f":5}]}],{"#f":1}],"Versuch2":[["^Kevin: Willkommen zurück. Du kommst mir gerade zur rechten Zeit. Steht dir der Sinn nach Arbeit? ","#","^kevin","/#","\n","ev","str","^Helfen","/str","/ev",{"*":".^.c-0","flg":4},"ev","str","^Gehen","/str","/ev",{"*":".^.c-1","flg":4},{"c-0":["^ Locus: Gut, ",{"->":"Kevin.HelfenA"},"\n",{"#f":5}],"c-1":["^ Locus: Ich vertreibe mir lieber anders die Zeit. ","#","^locus","/#","\n","end",{"#f":5}]}],{"#f":1}],"Stahlda":[["^Kevin: Freut mich dich wiederzusehen, mein kleiner Assistent. Hast du den <color=#58FF5E>Stahl</color> um den ich dich gebeten habe? ","#","^kevin","/#","\n","ev","str","^Noch nicht","/str","/ev",{"*":".^.c-0","flg":4},"ev","str","^Stahlbarren geben","/str","str","^item_stahl","/str",{"x()":"Get_State","exArgs":1},"/ev",{"*":".^.c-1","flg":21},"ev","str","^Schal geben","/str","str","^item_schal","/str",{"x()":"Get_State","exArgs":1},"/ev",{"*":".^.c-2","flg":21},{"c-0":["^ Locus: Noch nicht, ich werde mich schon bald darum kümmern. ","#","^locus","/#","\n","end",{"#f":5}],"c-1":[{"->":"Kevin.Loot"},"\n",{"#f":5}],"c-2":[{"->":"Kevin.Schal"},"\n",{"#f":5}]}],{"#f":1}],"Schal":["^Locus: Aber sicher doch, hier bitte. ","#","^locus","/#","\n","^Kevin: Ja aber was ist das denn?! Ich brauche <color=#58FF5E>Stahl</color> und keinen <color=#58FF5E>Schal</color>! Was hast du dir dabei gedacht? ","#","^kevin","/#","\n","^Kevin: Geh zurück zu <color=#66DBFF>Remus</color> und besorge mir meinen <color=#58FF5E>Höllenstahlbarren</color>! ","#","^kevin","/#","\n","ev","str","^Q-Kevin-5","/str",{"x()":"Unity_Event","exArgs":1},"pop","/ev","\n","end",{"#f":1}],"Jaromiri":["^Locus: Was ist mit <color=#66DBFF>Jaromir</color>? Warum lässt er mich nicht über die Brücke? ","#","^locus","/#","\n","ev","str","^Q-Jaromir-2","/str",{"x()":"Unity_Event","exArgs":1},"pop","/ev","\n","^Kevin: Er hat damit begonnen Abgaben zu verlangen. Da er nicht sehr gut sehen kann, bringe ich ihm immer etwas glänzendes als \"<color=#58FF5E>Tribut</color>\". ","#","^kevin","/#","\n",{"->":".^.^.Hub"},{"#f":1}],"Loot":[["ev","str","^item_stahl","/str",-1,{"x()":"Add_State","exArgs":2},"pop","/ev","\n","ev","str","^Q-Kevin-3","/str",{"x()":"Unity_Event","exArgs":1},"pop","/ev","\n","^Locus: Ja, hier bitte. ","#","^locus","/#","\n","^Kevin: Vorzüglich. Damit sollte ich das <color=#58FF5E>Zepter</color> fertigstellen können. Ich danke dir <color=#66DBFF>Locus</color>. ","#","^kevin","/#","\n","^Kevin: Als <color=#58FF5E>Belohnung</color> kannst du dir auch etwas wünschen. ","#","^kevin","/#","\n","ev","str","^Zepter","/str","/ev",{"*":".^.c-0","flg":20},"ev","str","^Teller","/str",{"CNT?":"Kevin.Fest"},"/ev",{"*":".^.c-1","flg":21},"ev","str","^Teller","/str",{"CNT?":"Kevin.Fest"},"!","/ev",{"*":".^.c-2","flg":21},"ev","str","^Nichts","/str","/ev",{"*":".^.c-3","flg":20},{"c-0":["^ ",{"->":"Kevin.Dreizack"},"\n",{"#f":5}],"c-1":["^ ",{"->":"Kevin.Teller"},"\n",{"#f":5}],"c-2":["^ ",{"->":"Kevin.WhyTeller"},"\n",{"#f":5}],"c-3":["^ Locus: Ich bin wunschlos glücklich. Ich brauche nichts.: ",{"->":"Kevin.Hub"},"\n",{"#f":5}]}],{"#f":1}],"Dreizack":[["^Locus: Ich möchste gerne das <color=#58FF5E>Zepter</color>. ","#","^locus","/#","\n","^Kevin: Bist du denn von Sinnen? Den kann ich dir keinesfalls überlassen! Such dir etwas anderes aus. ","#","^kevin","/#","\n","ev","str","^Teller","/str","/ev",{"*":".^.c-0","flg":20},"ev","str","^Nichts","/str","/ev",{"*":".^.c-1","flg":20},{"c-0":["^  ",{"->":"Kevin.Teller"},"\n",{"#f":5}],"c-1":["^ Locus: Ich bin wunschlos glücklich. Ich brauche nichts.: ",{"->":"Kevin.Hub"},"\n",{"#f":5}]}],{"#f":1}],"Teller":["^Locus: Ich würde gerne deine <color=#58FF5E>Teller</color> für das Fest nutzen. ","#","^locus","/#","\n","^Kevin: Gewiss doch, eine sehr weise Entscheidung. Ich hoffe es gelingt dir den <color=#66DBFF>Meister</color> zufrieden zu stellen. ","#","^kevin","/#","\n",{"->":".^.^.Hub"},{"#f":1}],"WhyTeller":[["^Locus: Ich würde gerne deine <color=#58FF5E>Teller</color> für ein Fest nutzen. ","#","^locus","/#","\n","^Kevin: Ein Fest? Was gibt es denn schönes zu feiern? ","#","^kevin","/#","\n","^Locus: Den Geburtstag unseres <color=#66DBFF>Meisters</color>. Er hat mich angeblich persönlich für diese Aufgabe auserwählt. ","#","^locus","/#","\n","^Kevin: Oh, dann gebe ich dir die <color=#58FF5E>Teller</color> gerne und wünsche dir viel Glück, du weisst ja was mit dem letzten geschah, der diese Aufgabe hatte... ","#","^kevin","/#","\n","ev","str","^Nein, was ist mit ihm?","/str","/ev",{"*":".^.c-0","flg":20},"ev","str","^Gehen","/str","/ev",{"*":".^.c-1","flg":20},{"c-0":[{"->":"Kevin.Victus"},"\n",{"#f":5}],"c-1":["^Locus: Das ist doch keine grosse Sache, ich krieg das schon hin mit der Feier. ","#","^locus","/#","\n","end",{"#f":5}]}],{"#f":1}],"Hub":[["^Kevin: Brauchst du noch etwas? ","#","^kevin","/#","\n","ev","str","^Brückenwächter","/str",{"CNT?":"Jaromir.Gruss"},"/ev",{"*":".^.c-0","flg":21},"ev","str","^Ich muss ein Fest organisieren","/str",{"CNT?":"Kevin.Fest"},"!",{"CNT?":"Kevin.WhyTeller"},"!","&&","/ev",{"*":".^.c-1","flg":21},"ev","str","^Ich brauche Teller","/str",{"CNT?":"Kevin.Teller"},"!",{"CNT?":"Kevin.Fest"},"&&","/ev",{"*":".^.c-2","flg":21},"ev","str","^Ich brauche Teller","/str",{"CNT?":"Kevin.Fest"},"!",{"CNT?":"Kevin.WhyTeller"},"!","&&","/ev",{"*":".^.c-3","flg":21},"ev","str","^Gehen","/str","/ev",{"*":".^.c-4","flg":4},{"c-0":["^ ",{"->":"Kevin.Jaromiri"},"\n",{"#f":5}],"c-1":[{"->":"Kevin.Fest"},"\n",{"#f":5}],"c-2":["^ ",{"->":"Kevin.Teller"},"\n",{"#f":5}],"c-3":["^ ",{"->":"Kevin.WhyTeller"},"\n",{"#f":5}],"c-4":["^ Locus: Nein, alles gut, bis bald. ","#","^locus","/#","\n","end",{"#f":5}]}],{"#f":1}],"#f":1}],"Jaromir":[{"->":".^.Start"},{"Start":["ev",{"CNT?":".^.^.Gruss"},"/ev",[{"->":".^.b","c":true},{"b":["^ ",{"->":"Jaromir.Hub"},{"->":".^.^.^.4"},null]}],"nop","\n",{"->":".^.^.Gruss"},{"#f":1}],"Gruss":[["^Jaromir: Geeebbbüüühhhrrreeennn! ","#","^jaromir","/#","\n","^Locus: Was? ","#","^locus","/#","\n","^Jaromir: Müüünnnzzzeeennn! ","#","^jaromir","/#","\n","ev","str","^Ich möchte über die Brücke","/str","/ev",{"*":".^.c-0","flg":20},"ev","str","^Gehen","/str","/ev",{"*":".^.c-1","flg":20},{"c-0":["^ ",{"->":"Jaromir.Brucke"},"\n",{"#f":5}],"c-1":["^ Locus: Sowas muss ich mir nicht antun. ","#","^locus","/#","\n","end",{"#f":5}]}],{"#f":1}],"Brucke":[["^Locus: Ich möchte über die Brücke. ","#","^locus","/#","\n","^Jaromir: Geeelllddd! ","#","^jaromir","/#","\n","ev","str","^Q-Jaromir-1","/str",{"x()":"Unity_Event","exArgs":1},"pop","/ev","\n","ev","str","^Du kannst mich mal","/str","/ev",{"*":".^.c-0","flg":20},"ev","str","^Gehen","/str","/ev",{"*":".^.c-1","flg":20},{"c-0":["^ ",{"->":"Jaromir.Agro"},"\n",{"#f":5}],"c-1":["^ Locus: Sowas muss ich mir nicht antun. ","#","^locus","/#","\n","end",{"#f":5}]}],{"#f":1}],"Agro":["^Locus: Du kannst mich mal! ","#","^locus","/#","\n","^Jaromir: Fiiinnnaaannnzzzeeennn! ","#","^jaromir","/#","\n","end",{"#f":1}],"Hub":[["^Jaromir: ",["ev","visit",14,"%","/ev","ev","du",0,"==","/ev",{"->":".^.s0","c":true},"ev","du",1,"==","/ev",{"->":".^.s1","c":true},"ev","du",2,"==","/ev",{"->":".^.s2","c":true},"ev","du",3,"==","/ev",{"->":".^.s3","c":true},"ev","du",4,"==","/ev",{"->":".^.s4","c":true},"ev","du",5,"==","/ev",{"->":".^.s5","c":true},"ev","du",6,"==","/ev",{"->":".^.s6","c":true},"ev","du",7,"==","/ev",{"->":".^.s7","c":true},"ev","du",8,"==","/ev",{"->":".^.s8","c":true},"ev","du",9,"==","/ev",{"->":".^.s9","c":true},"ev","du",10,"==","/ev",{"->":".^.s10","c":true},"ev","du",11,"==","/ev",{"->":".^.s11","c":true},"ev","du",12,"==","/ev",{"->":".^.s12","c":true},"ev","du",13,"==","/ev",{"->":".^.s13","c":true},"nop",{"s0":["pop","^Mooonnneeettteeennn!",{"->":".^.^.89"},null],"s1":["pop","^Zaaasssttteeerrr!",{"->":".^.^.89"},null],"s2":["pop","^Kooohhhllleee!",{"->":".^.^.89"},null],"s3":["pop","^Abbbgggaaabbbeeennn!",{"->":".^.^.89"},null],"s4":["pop","^Krrröööttteeennn!",{"->":".^.^.89"},null],"s5":["pop","^Asssccchhheee!",{"->":".^.^.89"},null],"s6":["pop","^Piiieeepppeeennn!",{"->":".^.^.89"},null],"s7":["pop","^Immmooobbbiiillliiieeennn!",{"->":".^.^.89"},null],"s8":["pop","^Määäuuussseee!",{"->":".^.^.89"},null],"s9":["pop","^Heeedddgggeeefffooonnndddsss!",{"->":".^.^.89"},null],"s10":["pop","^Krrryyyppptttooo!",{"->":".^.^.89"},null],"s11":["pop","^Gooolllddd!",{"->":".^.^.89"},null],"s12":["pop","^Knnneeettteee!",{"->":".^.^.89"},null],"s13":["pop","^Sccchhhhooottteeerrr!",{"->":".^.^.89"},null],"#f":5}],"^ ","#","^jaromir","/#","\n","ev","str","^Scherbe geben","/str","str","^item_scherbe","/str",{"x()":"Get_State","exArgs":1},"/ev",{"*":".^.c-0","flg":21},"ev","str","^Reifen geben","/str","str","^item_reifen","/str",{"x()":"Get_State","exArgs":1},"/ev",{"*":".^.c-1","flg":21},"ev","str","^Schokolade geben","/str","str","^item_schokolade","/str",{"x()":"Get_State","exArgs":1},"/ev",{"*":".^.c-2","flg":21},"ev","str","^Du kannst mich mal","/str",{"CNT?":".^.^.^.Agro"},"!","/ev",{"*":".^.c-3","flg":21},"ev","str","^Gehen","/str","/ev",{"*":".^.c-4","flg":4},{"c-0":["^ ",{"->":"Jaromir.Offen"},"\n",{"#f":5}],"c-1":["^ ",{"->":"Jaromir.Betrug1"},"\n",{"#f":5}],"c-2":["^ ",{"->":"Jaromir.Betrug2"},"\n",{"#f":5}],"c-3":["^ ",{"->":"Jaromir.Agro"},"\n",{"#f":5}],"c-4":["^ Locus: Aufwiederstehlen ","#","^locus","/#","\n","end",{"#f":5}]}],{"#f":1}],"Betrug1":["ev","str","^item_reifen","/str",-1,{"x()":"Add_State","exArgs":2},"pop","/ev","\n","^Locus: Hier nimm dein Geld! ","#","^locus","/#","\n","^Jaromir: Beeetttrrruuuggg! ","#","^jaromir","/#","\n","ev","str","^Minus","/str",{"x()":"Unity_Event","exArgs":1},"pop","/ev","\n","end",{"#f":1}],"Betrug2":["ev","str","^item_schokolade","/str",-1,{"x()":"Add_State","exArgs":2},"pop","/ev","\n","^Locus: Hier nimm dein Geld! ","#","^locus","/#","\n","^Jaromir: Beeetttrrruuuggg! ","#","^jaromir","/#","\n","ev","str","^Minus","/str",{"x()":"Unity_Event","exArgs":1},"pop","/ev","\n","end",{"#f":1}],"Offen":["ev","str","^item_scherbe","/str",-1,{"x()":"Add_State","exArgs":2},"pop","/ev","\n","^Locus: Hier nimm dein Geld! ","#","^locus","/#","\n","^Jaromir: Geeewwwiiinnnnnn! ","#","^jaromir","/#","\n","ev","str","^Brugg","/str",{"x()":"Unity_Event","exArgs":1},"pop","/ev","\n","end",{"#f":1}],"#f":1}],"Remus":[{"->":".^.Start"},{"Start":["ev",{"CNT?":".^.^.Gruss"},"/ev",[{"->":".^.b","c":true},{"b":["^ ",{"->":"Remus.Back"},{"->":".^.^.^.4"},null]}],"nop","\n",{"->":".^.^.Gruss"},{"#f":1}],"Gruss":[["^Remus: <color=#66DBFF>Locus</color>... Schön dich zu.. und so weiter und so weiter.","\n","<>","^ Ich sehe, dass du wieder nur am faulenzen bist. ","#","^remus","/#","\n","^Locus: Das stimmt doch gar nicht! ","#","^locus","/#","\n","^Remus: Wie auch immer. Heute bei der morgentlichen Sitzung kam ein Auftrag für dich rein. ","#","^remus","/#","\n","^Remus: Unser <color=#66DBFF>Meister</color>, der <color=#66DBFF>Teufel</color> höchst selbst erwählte dich, um sein Geburtstagsfeier zu organisieren. ","#","^remus","/#","\n","^Locus: Mich? Wieso muss ich das denn machen? ","#","^locus","/#","\n","^Remus: Laut meiner Liste ist der letzte der diese Aufgabe hatte, naja sagen wir er ist verhindert. ","#","^remus","/#","\n","<>","^ Ausserdem hast du momentan keine Verpflichtungen, seit dem du aus der Bestrafungsabteilung entlassen wurdest. ","#","^remus","/#","\n","ev","str","^Was muss ich tun?","/str","/ev",{"*":".^.c-0","flg":20},"ev","str","^Aufgabe weitergeben?","/str","/ev",{"*":".^.c-1","flg":20},{"c-0":["^ ",{"->":"Remus.QuestTun"},"\n",{"#f":5}],"c-1":["^ ",{"->":"Remus.Weitergeben"},"\n",{"#f":5}]}],{"#f":1}],"Weitergeben":["^Locus: Kann das nicht jemand anderes erledigen? ","#","^locus","/#","\n","^Remus: Nein... Denkst du etwa ich bin mit meiner Aufgabe zufrieden? Tag für Tag muss ich mich mit Leuten wie dir abgeben. ","#","^remus","/#","\n",{"->":".^.^.QuestTun"},{"#f":1}],"QuestTun":[["^Locus: Also was genau möchte er für sein Fest? ","#","^locus","/#","\n","^Remus: Abgesehen vom <color=#58FF5E>Geschirr</color>, den <color=#58FF5E>Getränken</color> und einem <color=#58FF5E>Kuchen</color> möchte der <color=#66DBFF>Meister</color> nur ein paar <color=#58FF5E>Ballons</color> zu seinem Fest... ","#","^remus","/#","\n","^Remus: Alles was du gesammelt hast kannst du auf diesem <color=#58FF5E>Tisch</color> lagern. Ich habe dir bereits einige <color=#58FF5E>Kerzen</color> hinterlegt. ","#","^remus","/#","\n","ev","str","^Q-Remus-1","/str",{"x()":"Unity_Event","exArgs":1},"pop","/ev","\n","^Remus: Sobald du bereit bist und ich den <color=#66DBFF>Meister</color> rufen kann, melde dich... ","#","^remus","/#","\n","ev","str","^Was muss ich tun?","/str","/ev",{"*":".^.c-0","flg":4},"ev","str","^Geschirr?","/str","str","^item_teller","/str",{"x()":"Get_State","exArgs":1},"!","/ev",{"*":".^.c-1","flg":5},"ev","str","^Getränke?","/str","/ev",{"*":".^.c-2","flg":4},"ev","str","^Kuchen?","/str","/ev",{"*":".^.c-3","flg":4},"ev","str","^Ballons?","/str","/ev",{"*":".^.c-4","flg":4},"ev","str","^Ich brauche Stahl","/str",{"CNT?":"Kevin.HelfenA"},{"CNT?":"Remus.getSchal"},"!","&&",{"CNT?":"Remus.getStahl"},"!","&&",{"CNT?":"Kevin.Loot"},"!","&&","/ev",{"*":".^.c-5","flg":21},"ev","str","^Ich brauche Stahl","/str",{"CNT?":"Kevin.Schal"},{"CNT?":"Kevin.Loot"},"!","&&","/ev",{"*":".^.c-6","flg":21},"ev","str","^Ich brauche einen Schal","/str",{"CNT?":"Kevin.HelfenA"},{"CNT?":"Remus.getStahl"},"!","&&",{"CNT?":"Kevin.Loot"},"!","&&","/ev",{"*":".^.c-7","flg":21},"ev","str","^Gehen","/str","/ev",{"*":".^.c-8","flg":4},{"c-0":["^ ",{"->":"Remus.WasTun"},"\n",{"#f":5}],"c-1":["^ ",{"->":"Remus.Geschirr"},"\n",{"#f":5}],"c-2":["^ ",{"->":"Remus.Getranke"},"\n",{"#f":5}],"c-3":["^ ",{"->":"Remus.Kuchen"},"\n",{"#f":5}],"c-4":["^ ",{"->":"Remus.Ballons"},"\n",{"#f":5}],"c-5":["^ ",{"->":"Remus.getStahl"},"\n",{"#f":5}],"c-6":["^ ",{"->":"Remus.dochStahl"},"\n",{"#f":5}],"c-7":["^ ",{"->":"Remus.getSchal"},"\n",{"#f":5}],"c-8":["^Locus: Ich mach mich dann mal ans Werk! ","#","^locus","/#","\n","end",{"#f":5}]}],{"#f":1}],"WasTun":[["^Locus: Also was genau möchte er für sein Fest? ","#","^locus","/#","\n","^Remus: Abgesehen vom <color=#58FF5E>Geschirr</color>, den <color=#58FF5E>Getränken</color> und einem <color=#58FF5E>Kuchen</color> möchte der <color=#66DBFF>Meister</color> nur ein paar <color=#58FF5E>Ballons</color> zu seinem Fest... ","#","^remus","/#","\n","^Remus: Sobald du bereit bist und ich den <color=#66DBFF>Meister</color> rufen kann, melde dich... ","#","^remus","/#","\n","ev","str","^Was muss ich tun?","/str","/ev",{"*":".^.c-0","flg":4},"ev","str","^Geschirr?","/str","str","^item_teller","/str",{"x()":"Get_State","exArgs":1},"!","/ev",{"*":".^.c-1","flg":5},"ev","str","^Getränke?","/str","/ev",{"*":".^.c-2","flg":4},"ev","str","^Kuchen?","/str","/ev",{"*":".^.c-3","flg":4},"ev","str","^Ballons?","/str","/ev",{"*":".^.c-4","flg":4},"ev","str","^Ich brauche Stahl","/str",{"CNT?":"Kevin.HelfenA"},{"CNT?":"Remus.getSchal"},"!","&&",{"CNT?":"Remus.getStahl"},"!","&&",{"CNT?":"Kevin.Loot"},"!","&&","/ev",{"*":".^.c-5","flg":21},"ev","str","^Ich brauche Stahl","/str",{"CNT?":"Kevin.Schal"},{"CNT?":"Kevin.Loot"},"!","&&","/ev",{"*":".^.c-6","flg":21},"ev","str","^Ich brauche einen Schal","/str",{"CNT?":"Kevin.HelfenA"},{"CNT?":"Remus.getStahl"},"!","&&",{"CNT?":"Kevin.Loot"},"!","&&","/ev",{"*":".^.c-7","flg":21},"ev","str","^Gehen","/str","/ev",{"*":".^.c-8","flg":4},{"c-0":["^ ",{"->":".^.^.^"},"\n",{"#f":5}],"c-1":["^ ",{"->":"Remus.Geschirr"},"\n",{"#f":5}],"c-2":["^ ",{"->":"Remus.Getranke"},"\n",{"#f":5}],"c-3":["^ ",{"->":"Remus.Kuchen"},"\n",{"#f":5}],"c-4":["^ ",{"->":"Remus.Ballons"},"\n",{"#f":5}],"c-5":["^ ",{"->":"Remus.getStahl"},"\n",{"#f":5}],"c-6":["^ ",{"->":"Remus.dochStahl"},"\n",{"#f":5}],"c-7":["^ ",{"->":"Remus.getSchal"},"\n",{"#f":5}],"c-8":["^Locus: Ich mach mich dann mal ans Werk! ","#","^locus","/#","\n","end",{"#f":5}]}],{"#f":1}],"Geschirr":[["^Locus: Woher soll ich das <color=#58FF5E>Geschirr</color> nehmen? ","#","^locus","/#","\n","^Remus: Soweit ich weiss sollte <color=#66DBFF>Kevin</color> in seiner <color=#58FF5E>Werkstatt</color> etwas haben... ","#","^remus","/#","\n","ev","str","^Was muss ich tun?","/str","/ev",{"*":".^.c-0","flg":4},"ev","str","^Geschirr?","/str","str","^item_teller","/str",{"x()":"Get_State","exArgs":1},"!","/ev",{"*":".^.c-1","flg":5},"ev","str","^Getränke?","/str","/ev",{"*":".^.c-2","flg":4},"ev","str","^Kuchen?","/str","/ev",{"*":".^.c-3","flg":4},"ev","str","^Ballons?","/str","/ev",{"*":".^.c-4","flg":4},"ev","str","^Ich brauche Stahl","/str",{"CNT?":"Kevin.HelfenA"},{"CNT?":"Remus.getStahl"},"!","&&",{"CNT?":"Remus.getSchal"},"!","&&",{"CNT?":"Kevin.Loot"},"!","&&","/ev",{"*":".^.c-5","flg":21},"ev","str","^Ich brauche Stahl","/str",{"CNT?":"Kevin.Schal"},{"CNT?":"Kevin.Loot"},"!","&&","/ev",{"*":".^.c-6","flg":21},"ev","str","^Ich brauche einen Schal","/str",{"CNT?":"Kevin.HelfenA"},{"CNT?":"Remus.getStahl"},"!","&&","/ev",{"*":".^.c-7","flg":21},"ev","str","^Gehen","/str","/ev",{"*":".^.c-8","flg":4},{"c-0":["^ ",{"->":"Remus.WasTun"},"\n",{"#f":5}],"c-1":["^ ",{"->":".^.^.^"},"\n",{"#f":5}],"c-2":["^ ",{"->":"Remus.Getranke"},"\n",{"#f":5}],"c-3":["^ ",{"->":"Remus.Kuchen"},"\n",{"#f":5}],"c-4":["^ ",{"->":"Remus.Ballons"},"\n",{"#f":5}],"c-5":["^ ",{"->":"Remus.getStahl"},"\n",{"#f":5}],"c-6":["^ ",{"->":"Remus.dochStahl"},"\n",{"#f":5}],"c-7":["^ ",{"->":"Remus.getSchal"},"\n",{"#f":5}],"c-8":["^Locus: Ich mach mich dann mal ans Werk! ","#","^locus","/#","\n","end",{"#f":5}]}],{"#f":1}],"Getranke":[["^Locus: Wie komme ich zu <color=#58FF5E>Getränken</color>? Und was möchte der <color=#66DBFF>Chef</color> denn überhaupt trinken? ","#","^locus","/#","\n","^Remus: Woher soll ich das wissen? Sehe ich aus wie sein Mundschenk? Ich denke solange es flüssig ist wird es schon passen. ","#","^remus","/#","\n","ev","str","^Was muss ich tun?","/str","/ev",{"*":".^.c-0","flg":4},"ev","str","^Geschirr?","/str","str","^item_teller","/str",{"x()":"Get_State","exArgs":1},"!","/ev",{"*":".^.c-1","flg":5},"ev","str","^Getränke?","/str","/ev",{"*":".^.c-2","flg":4},"ev","str","^Kuchen?","/str","/ev",{"*":".^.c-3","flg":4},"ev","str","^Ballons?","/str","/ev",{"*":".^.c-4","flg":4},"ev","str","^Ich brauche Stahl","/str",{"CNT?":"Kevin.HelfenA"},{"CNT?":"Remus.getStahl"},"!","&&",{"CNT?":"Remus.getSchal"},"!","&&",{"CNT?":"Kevin.Loot"},"!","&&","/ev",{"*":".^.c-5","flg":21},"ev","str","^Ich brauche Stahl","/str",{"CNT?":"Kevin.Schal"},{"CNT?":"Kevin.Loot"},"!","&&","/ev",{"*":".^.c-6","flg":21},"ev","str","^Ich brauche einen Schal","/str",{"CNT?":"Kevin.HelfenA"},{"CNT?":"Remus.getStahl"},"!","&&","/ev",{"*":".^.c-7","flg":21},"ev","str","^Gehen","/str","/ev",{"*":".^.c-8","flg":4},{"c-0":["^ ",{"->":"Remus.WasTun"},"\n",{"#f":5}],"c-1":["^ ",{"->":"Remus.Geschirr"},"\n",{"#f":5}],"c-2":["^ ",{"->":".^.^.^"},"\n",{"#f":5}],"c-3":["^ ",{"->":"Remus.Kuchen"},"\n",{"#f":5}],"c-4":["^ ",{"->":"Remus.Ballons"},"\n",{"#f":5}],"c-5":["^ ",{"->":"Remus.getStahl"},"\n",{"#f":5}],"c-6":["^ ",{"->":"Remus.dochStahl"},"\n",{"#f":5}],"c-7":["^ ",{"->":"Remus.getSchal"},"\n",{"#f":5}],"c-8":["^Locus: Ich mach mich dann mal ans Werk! ","#","^locus","/#","\n","end",{"#f":5}]}],{"#f":1}],"Kuchen":[["^Locus: Hast du einen <color=#58FF5E>Kuchen</color>? ","#","^locus","/#","\n","^Remus: Jetzt wirds lächerlich. ","#","^remus","/#","\n","ev","str","^Was muss ich tun?","/str","/ev",{"*":".^.c-0","flg":4},"ev","str","^Geschirr?","/str","str","^item_teller","/str",{"x()":"Get_State","exArgs":1},"!","/ev",{"*":".^.c-1","flg":5},"ev","str","^Getränke?","/str","/ev",{"*":".^.c-2","flg":4},"ev","str","^Kuchen?","/str","/ev",{"*":".^.c-3","flg":4},"ev","str","^Ballons?","/str","/ev",{"*":".^.c-4","flg":4},"ev","str","^Ich brauche Stahl","/str",{"CNT?":"Kevin.HelfenA"},{"CNT?":"Remus.getStahl"},"!","&&",{"CNT?":"Remus.getSchal"},"!","&&",{"CNT?":"Kevin.Loot"},"!","&&","/ev",{"*":".^.c-5","flg":21},"ev","str","^Ich brauche Stahl","/str",{"CNT?":"Kevin.Schal"},{"CNT?":"Kevin.Loot"},"!","&&","/ev",{"*":".^.c-6","flg":21},"ev","str","^Ich brauche einen Schal","/str",{"CNT?":"Kevin.HelfenA"},{"CNT?":"Remus.getStahl"},"!","&&","/ev",{"*":".^.c-7","flg":21},"ev","str","^Gehen","/str","/ev",{"*":".^.c-8","flg":4},{"c-0":["^ ",{"->":"Remus.WasTun"},"\n",{"#f":5}],"c-1":["^ ",{"->":"Remus.Geschirr"},"\n",{"#f":5}],"c-2":["^ ",{"->":"Remus.Getranke"},"\n",{"#f":5}],"c-3":["^ ",{"->":".^.^.^"},"\n",{"#f":5}],"c-4":["^ ",{"->":"Remus.Ballons"},"\n",{"#f":5}],"c-5":["^ ",{"->":"Remus.getStahl"},"\n",{"#f":5}],"c-6":["^ ",{"->":"Remus.dochStahl"},"\n",{"#f":5}],"c-7":["^ ",{"->":"Remus.getSchal"},"\n",{"#f":5}],"c-8":["^Locus: Ich mach mich dann mal ans Werk! ","#","^locus","/#","\n","end",{"#f":5}]}],{"#f":1}],"Ballons":[["^Locus: Wo würdest du nach <color=#58FF5E>Ballons</color> suchen? ","#","^locus","/#","\n","^Remus: <color=#66DBFF>Seth</color>, der Schädel benutzt einige um auf Augenhöhe mit allen reden zu können. Ich denke aber nicht, dass er diese so leicht hergibt. ","#","^remus","/#","\n","ev","str","^Was muss ich tun?","/str","/ev",{"*":".^.c-0","flg":4},"ev","str","^Geschirr?","/str","str","^item_teller","/str",{"x()":"Get_State","exArgs":1},"!","/ev",{"*":".^.c-1","flg":5},"ev","str","^Getränke?","/str","/ev",{"*":".^.c-2","flg":4},"ev","str","^Kuchen?","/str","/ev",{"*":".^.c-3","flg":4},"ev","str","^Ballons?","/str","/ev",{"*":".^.c-4","flg":4},"ev","str","^Ich brauche Stahl","/str",{"CNT?":"Kevin.HelfenA"},{"CNT?":"Remus.getStahl"},"!","&&",{"CNT?":"Remus.getSchal"},"!","&&",{"CNT?":"Kevin.Loot"},"!","&&","/ev",{"*":".^.c-5","flg":21},"ev","str","^Ich brauche Stahl","/str",{"CNT?":"Kevin.Schal"},{"CNT?":"Kevin.Loot"},"!","&&","/ev",{"*":".^.c-6","flg":21},"ev","str","^Ich brauche einen Schal","/str",{"CNT?":"Kevin.HelfenA"},{"CNT?":"Remus.getStahl"},"!","&&","/ev",{"*":".^.c-7","flg":21},"ev","str","^Gehen","/str","/ev",{"*":".^.c-8","flg":4},{"c-0":["^ ",{"->":"Remus.WasTun"},"\n",{"#f":5}],"c-1":["^ ",{"->":"Remus.Geschirr"},"\n",{"#f":5}],"c-2":["^ ",{"->":"Remus.Getranke"},"\n",{"#f":5}],"c-3":["^ ",{"->":"Remus.Kuchen"},"\n",{"#f":5}],"c-4":["^ ",{"->":".^.^.^"},"\n",{"#f":5}],"c-5":["^ ",{"->":"Remus.getStahl"},"\n",{"#f":5}],"c-6":["^ ",{"->":"Remus.dochStahl"},"\n",{"#f":5}],"c-7":["^ ",{"->":"Remus.getSchal"},"\n",{"#f":5}],"c-8":["^Locus: Ich mach mich dann mal ans Werk! ","#","^locus","/#","\n","end",{"#f":5}]}],{"#f":1}],"Back":[["^Remus: ",["ev","visit",4,"%","/ev","ev","du",0,"==","/ev",{"->":".^.s0","c":true},"ev","du",1,"==","/ev",{"->":".^.s1","c":true},"ev","du",2,"==","/ev",{"->":".^.s2","c":true},"ev","du",3,"==","/ev",{"->":".^.s3","c":true},"nop",{"s0":["pop","^Was kann ich gegen dich tun?",{"->":".^.^.29"},null],"s1":["pop","^Was denn noch?",{"->":".^.^.29"},null],"s2":["pop","^Bitte lass mich in Ruhe...",{"->":".^.^.29"},null],"s3":["pop","^Was denn nun schon wieder?",{"->":".^.^.29"},null],"#f":5}],"^ ","#","^remus","/#","\n","ev","str","^Was muss ich tun?","/str","/ev",{"*":".^.c-0","flg":4},"ev","str","^Geschirr?","/str","str","^item_teller","/str",{"x()":"Get_State","exArgs":1},"!","/ev",{"*":".^.c-1","flg":5},"ev","str","^Getränke?","/str","/ev",{"*":".^.c-2","flg":4},"ev","str","^Kuchen?","/str","/ev",{"*":".^.c-3","flg":4},"ev","str","^Ballons?","/str","/ev",{"*":".^.c-4","flg":4},"ev","str","^Ich brauche Stahl","/str",{"CNT?":"Kevin.HelfenA"},{"CNT?":"Remus.getStahl"},"!","&&",{"CNT?":"Remus.getSchal"},"!","&&",{"CNT?":"Kevin.Loot"},"!","&&","/ev",{"*":".^.c-5","flg":21},"ev","str","^Ich brauche Stahl","/str",{"CNT?":"Kevin.Schal"},{"CNT?":"Kevin.Loot"},"!","&&","/ev",{"*":".^.c-6","flg":21},"ev","str","^Ich brauche einen Schal","/str",{"CNT?":"Kevin.HelfenA"},{"CNT?":"Remus.getStahl"},"!","&&","/ev",{"*":".^.c-7","flg":21},"ev","str","^Gehen","/str","/ev",{"*":".^.c-8","flg":4},{"c-0":["^ ",{"->":"Remus.WasTun"},"\n",{"#f":5}],"c-1":["^ ",{"->":"Remus.Geschirr"},"\n",{"#f":5}],"c-2":["^ ",{"->":"Remus.Getranke"},"\n",{"#f":5}],"c-3":["^ ",{"->":"Remus.Kuchen"},"\n",{"#f":5}],"c-4":["^ ",{"->":"Remus.Ballons"},"\n",{"#f":5}],"c-5":["^ ",{"->":"Remus.getStahl"},"\n",{"#f":5}],"c-6":["^ ",{"->":"Remus.dochStahl"},"\n",{"#f":5}],"c-7":["^ ",{"->":"Remus.getSchal"},"\n",{"#f":5}],"c-8":["^Locus: ",["ev","visit",1,"MIN","/ev","ev","du",0,"==","/ev",{"->":".^.s0","c":true},"ev","du",1,"==","/ev",{"->":".^.s1","c":true},"nop",{"s0":["pop","^Ich mach mich dann mal ans Werk!",{"->":".^.^.17"},null],"s1":["pop","^Bis dann!",{"->":".^.^.17"},null],"#f":5}],"^ ","#","^locus","/#","\n","end",{"#f":5}]}],{"#f":1}],"getStahl":["^Locus: Ich komme im Namen von <color=#66DBFF>Kevin</color>, er braucht noch einen <color=#58FF5E>Höllenstahlbarren</color> um eine Arbeit für den <color=#66DBFF>Meister</color> zu vollenden. ","#","^locus","/#","\n","^Remus: Gut, hier nimm ihn, lass ihn aber nicht aus den Augen. Ich wage mir nicht vorzustellen was passieren würde solltest du ihn verlieren. ","#","^remus","/#","\n","ev","str","^item_stahl","/str",1,{"x()":"Add_State","exArgs":2},"pop","/ev","\n","ev","str","^Q-Kevin-2","/str",{"x()":"Unity_Event","exArgs":1},"pop","/ev","\n","end",{"#f":1}],"getSchal":["^Locus: Ich komme im Namen von <color=#66DBFF>Kevin</color>, er braucht einen <color=#58FF5E>Schal</color>. ","#","^locus","/#","\n","^Remus: Einen Schal? Reicht ihm die Hitze der Hölle nicht aus? Wieso um alles in der Welt würde er sowas wollen? ","#","^remus","/#","\n","^Locus: Ich muss gestehen, dass ich nicht recht zugehört habe als er mir alles erklärt hat. Aber es sei auch irgendwie für den <color=#66DBFF>Meister</color>. ","#","^locus","/#","\n","^Remus: Naja wenn es für den <color=#66DBFF>Meister</color> ist, will ich mal nicht so sein. Hier nimm deinen <color=#58FF5E>Schal</color>. ","#","^remus","/#","\n","ev","str","^item_schal","/str",1,{"x()":"Add_State","exArgs":2},"pop","/ev","\n","ev","str","^Q-Kevin-4","/str",{"x()":"Unity_Event","exArgs":1},"pop","/ev","\n","end",{"#f":1}],"dochStahl":["^Locus: Um ein entstandenes Missverständnis aufzulösen bräuchte ich einen <color=#58FF5E>Höllenstahlbarren</color>. ","#","^locus","/#","\n","^Remus: Einen Höllenstahlbarren? Weisst du wie wertvoll die sind? Was willst du überhaupt damit? ","#","^remus","/#","\n","^Locus: Weisst du noch als ich diesen <color=#58FF5E>Schal</color> wollte? ","#","^locus","/#","\n","^Remus: Du willst mir aber nicht sagen, dass du <color=#58FF5E>Stahl</color> und <color=#58FF5E>Schal</color> verwechselt hast?! ","#","^remus","/#","\n","^Locus: Ich habe gehört sowas passiert den Besten. ","#","^locus","/#","\n","^Remus: Ich denke, dass dein Gehör sein könnte. Aber nun ergibt das auch einen gewissen Sinn. Hier nimm den <color=#58FF5E>Barren</color>, aber achte gut darauf. ","#","^remus","/#","\n","ev","str","^item_stahl","/str",1,{"x()":"Add_State","exArgs":2},"pop","/ev","\n","ev","str","^Q-Kevin-2","/str",{"x()":"Unity_Event","exArgs":1},"pop","/ev","\n","end",{"#f":1}],"#f":1}],"Scherbe":[{"->":".^.Start"},{"Start":["ev",{"CNT?":"Jaromir.Offen"},"/ev",[{"->":".^.b","c":true},{"b":["^ ",{"->":"Scherbe.Stage4"},{"->":".^.^.^.4"},null]}],"nop","\n","ev",{"CNT?":".^.^.Nehmen"},"/ev",[{"->":".^.b","c":true},{"b":["^ ",{"->":"Scherbe.Stage3"},{"->":".^.^.^.10"},null]}],"nop","\n","ev",{"CNT?":"Kevin.Jaromiri"},"/ev",[{"->":".^.b","c":true},{"b":["^ ",{"->":"Scherbe.Stage2"},{"->":".^.^.^.16"},null]}],"nop","\n",{"->":".^.^.Stage1"},{"#f":1}],"Stage1":[["^Locus: Ein Fass voller Scherben. Was das wohl mal war? ","#","^thought","/#","\n","ev","str","^Nehmen","/str","/ev",{"*":".^.c-0","flg":4},"ev","str","^Gehen","/str","/ev",{"*":".^.c-1","flg":4},{"c-0":[{"->":"Scherbe.Warum"},"\n",{"#f":5}],"c-1":["end","\n",{"#f":5}]}],{"#f":1}],"Stage2":[["^Locus: Ein Fass voller Scherben. Was das wohl mal war? ","#","^thought","/#","\n","ev","str","^Nehmen","/str","/ev",{"*":".^.c-0","flg":4},"ev","str","^Gehen","/str","/ev",{"*":".^.c-1","flg":4},{"c-0":["\n","ev","str","^item_reifen","/str",{"x()":"Get_State","exArgs":1},"str","^item_schokolade","/str",{"x()":"Get_State","exArgs":1},"||","/ev",[{"->":".^.b","c":true},{"b":["^ ",{"->":"Scherbe.Voll"},{"->":".^.^.^.14"},null]}],[{"->":".^.b"},{"b":["^ ",{"->":"Scherbe.Nehmen"},{"->":".^.^.^.14"},null]}],"nop","\n",{"#f":5}],"c-1":["end","\n",{"#f":5}]}],{"#f":1}],"Warum":["^Locus: Nein, ich bin keine mobile Müllhalde. ","#","^thought","/#","\n","end",{"#f":1}],"Nehmen":["ev","str","^item_scherbe","/str",1,{"x()":"Add_State","exArgs":2},"pop","/ev","\n","ev","str","^TakeS","/str",{"x()":"Unity_Event","exArgs":1},"pop","/ev","\n","^Locus: Dann wollen wir mal unsere \"Brückenmaut\" bezahlen gehen. ","#","^thought","/#","\n","end",{"#f":1}],"Voll":["^Locus: Nein, ich habe bereits etwas mit dem ich Jaromir überlisten möchte. ","#","^thought","/#","\n","end",{"#f":1}],"Stage3":["^Locus: Noch mehr Scherben brauche ich nicht. Eine wird reichen müssen. Ich muss sie nur noch Jaromir bringen. ","#","^thought","/#","\n","end",{"#f":1}],"Stage4":["^Locus: Noch mehr Scherben brauche ich nicht. Ich kann bereits frei die Brücke passieren. ","#","^thought","/#","\n","end",{"#f":1}],"#f":1}],"Reifen":[{"->":".^.Start"},{"Start":["ev",{"CNT?":"Jaromir.Offen"},"/ev",[{"->":".^.b","c":true},{"b":["^ ",{"->":"Reifen.Stage4"},{"->":".^.^.^.4"},null]}],"nop","\n","ev",{"CNT?":"Jaromir.Betrug1"},"/ev",[{"->":".^.b","c":true},{"b":["^ ",{"->":"Reifen.Falsch1"},{"->":".^.^.^.10"},null]}],"nop","\n","ev",{"CNT?":".^.^.Nehmen"},"/ev",[{"->":".^.b","c":true},{"b":["^ ",{"->":"Reifen.Stage3"},{"->":".^.^.^.16"},null]}],"nop","\n","ev",{"CNT?":"Kevin.Jaromiri"},"/ev",[{"->":".^.b","c":true},{"b":["^ ",{"->":"Reifen.Stage2"},{"->":".^.^.^.22"},null]}],"nop","\n",{"->":".^.^.Stage1"},{"#f":1}],"Stage1":[["^Locus: Ein Fass voller Reifenschnitzel. Wer würde sowas in einem Fass lagern? ","#","^thought","/#","\n","ev","str","^Nehmen","/str","/ev",{"*":".^.c-0","flg":4},"ev","str","^Gehen","/str","/ev",{"*":".^.c-1","flg":4},{"c-0":[{"->":"Reifen.Warum"},"\n",{"#f":5}],"c-1":["end","\n",{"#f":5}]}],{"#f":1}],"Stage2":[["^Locus: Ein Fass voller Reifenschnitzel. Wer würde sowas in einem Fass lagern? ","#","^thought","/#","\n","ev","str","^Nehmen","/str","/ev",{"*":".^.c-0","flg":4},"ev","str","^Gehen","/str","/ev",{"*":".^.c-1","flg":4},{"c-0":["\n","ev","str","^item_schokolade","/str",{"x()":"Get_State","exArgs":1},"str","^item_scherbe","/str",{"x()":"Get_State","exArgs":1},"||","/ev",[{"->":".^.b","c":true},{"b":["^ ",{"->":"Reifen.Voll"},{"->":".^.^.^.14"},null]}],[{"->":".^.b"},{"b":["^ ",{"->":"Reifen.Nehmen"},{"->":".^.^.^.14"},null]}],"nop","\n",{"#f":5}],"c-1":["end","\n",{"#f":5}]}],{"#f":1}],"Warum":["^Locus: Nein, ich habe schon lange kein Auto mehr. ","#","^thought","/#","\n","end",{"#f":1}],"Nehmen":["ev","str","^item_reifen","/str",1,{"x()":"Add_State","exArgs":2},"pop","/ev","\n","ev","str","^TakeR","/str",{"x()":"Unity_Event","exArgs":1},"pop","/ev","\n","^Locus: Dann wollen wir mal unsere \"Brückenmaut\" bezahlen gehen. ","#","^thought","/#","\n","end",{"#f":1}],"Voll":["^Locus: Nein, ich habe bereits etwas mit dem ich Jaromir überlisten möchte. ","#","^thought","/#","\n","end",{"#f":1}],"Stage3":["^Locus: Noch mehr Reifenteile brauche ich nicht. Eine wird reichen müssen. Ich muss sie nur noch Jaromir bringen. ","#","^thought","/#","\n","end",{"#f":1}],"Falsch1":["^Locus: Das habe ich bereits versucht, aber Jaromir hat mich durchschaut. Ich sollte etwas anderes versuchen. Kevin meinte, ich brauche etwas glänzendes... ","#","^thought","/#","\n","end",{"#f":1}],"Stage4":["^Locus: Noch mehr Reifenteile brauche ich nicht. Ich kann bereits frei die Brücke passieren. ","#","^thought","/#","\n","end",{"#f":1}],"#f":1}],"Schokolade":[{"->":".^.Start"},{"Start":["ev",{"CNT?":"Jaromir.Offen"},"/ev",[{"->":".^.b","c":true},{"b":["^ ",{"->":".^.^.^.^.Stage4"},{"->":".^.^.^.4"},null]}],"nop","\n","ev",{"CNT?":"Jaromir.Betrug2"},"/ev",[{"->":".^.b","c":true},{"b":["^ ",{"->":".^.^.^.^.Falsch2"},{"->":".^.^.^.10"},null]}],"nop","\n","ev",{"CNT?":".^.^.Nehmen"},"/ev",[{"->":".^.b","c":true},{"b":["^ ",{"->":".^.^.^.^.Stage3"},{"->":".^.^.^.16"},null]}],"nop","\n","ev",{"CNT?":"Kevin.Jaromiri"},"/ev",[{"->":".^.b","c":true},{"b":["^ ",{"->":".^.^.^.^.Stage2"},{"->":".^.^.^.22"},null]}],"nop","\n",{"->":".^.^.Stage1"},{"#f":1}],"Stage1":[["^Locus: Ein Fass voller Schokolade. Das sollte wohl zum Himmel, da ist der Lieferant wohl falsch abgebogen. ","#","^thought","/#","\n","ev","str","^Nehmen","/str","/ev",{"*":".^.c-0","flg":4},"ev","str","^Gehen","/str","/ev",{"*":".^.c-1","flg":4},{"c-0":[{"->":".^.^.^.^.Warum"},"\n",{"#f":5}],"c-1":["end","\n",{"#f":5}]}],{"#f":1}],"Stage2":[["^Locus: Ein Fass voller Schokolade. Das sollte wohl zum Himmel, da ist der Lieferant wohl falsch abgebogen. ","#","^thought","/#","\n","ev","str","^Nehmen","/str","/ev",{"*":".^.c-0","flg":4},"ev","str","^Gehen","/str","/ev",{"*":".^.c-1","flg":4},{"c-0":["\n","ev","str","^item_reifen","/str",{"x()":"Get_State","exArgs":1},"str","^item_scherbe","/str",{"x()":"Get_State","exArgs":1},"||","/ev",[{"->":".^.b","c":true},{"b":["^ ",{"->":"Schokolade.Voll"},{"->":".^.^.^.14"},null]}],[{"->":".^.b"},{"b":["^ ",{"->":"Schokolade.Nehmen"},{"->":".^.^.^.14"},null]}],"nop","\n",{"#f":5}],"c-1":["end","\n",{"#f":5}]}],{"#f":1}],"Warum":["^Locus: Nein, ich habe keinen Hunger. ","#","^thought","/#","\n","end",{"#f":1}],"Nehmen":["ev","str","^item_schokolade","/str",1,{"x()":"Add_State","exArgs":2},"pop","/ev","\n","ev","str","^TakeSch","/str",{"x()":"Unity_Event","exArgs":1},"pop","/ev","\n","^Locus: Dann wollen wir mal unsere \"Brückenmaut\" bezahlen gehen. ","#","^thought","/#","\n","end",{"#f":1}],"Voll":["^Locus: Nein, ich habe bereits etwas mit dem ich Jaromir überlisten möchte. ","#","^thought","/#","\n","end",{"#f":1}],"Stage3":["^Locus: Noch mehr Schokolade brauche ich nicht. Eine Tafel wird reichen müssen. Ich muss sie nur noch Jaromir bringen. ","#","^thought","/#","\n","end",{"#f":1}],"Falsch2":["^Locus: Das habe ich bereits versucht, aber Jaromir hat mich durchschaut. Ich sollte etwas anderes versuchen. Kevin meinte, ich brauche etwas glänzendes... ","#","^thought","/#","\n","end",{"#f":1}],"Stage4":["^Locus: Noch mehr Schokolade brauche ich nicht. Ich kann bereits frei die Brücke passieren. ","#","^thought","/#","\n","end",{"#f":1}],"#f":1}],"TellerInspect":[{"->":".^.Start"},{"Start":["ev",{"CNT?":"Kevin.Teller"},"/ev",[{"->":".^.b","c":true},{"b":["^ ",{"->":".^.^.^.^.Take"},{"->":".^.^.^.4"},null]}],"nop","\n","ev",{"CNT?":"Kevin.WhyTeller"},"/ev",[{"->":".^.b","c":true},{"b":["^ ",{"->":".^.^.^.^.Take"},{"->":".^.^.^.10"},null]}],"nop","\n","ev",{"CNT?":"Remus.Gruss"},"/ev",[{"->":".^.b","c":true},{"b":["^ ",{"->":".^.^.^.^.After"},{"->":".^.^.^.16"},null]}],"nop","\n",{"->":".^.^.Pre"},{"#f":1}],"Pre":["^Locus: Ein paar öde Teller... ","#","^thought","/#","\n","end",{"#f":1}],"After":["^Locus: Mit Kevins Erlaubnis, könnte ich diese Teller für das Fest meines Meisters nutzen.","#","^thought","/#","\n","end",{"#f":1}],"Take":["ev","str","^Teller","/str",{"x()":"Unity_Event","exArgs":1},"pop","/ev","\n","ev","str","^item_teller","/str",1,{"x()":"Add_State","exArgs":2},"pop","/ev","\n","^Locus: Damit sollte ich genug Geschirr für das Fest haben. ","#","^thought","/#","\n","end",{"#f":1}],"#f":1}],"Seth":[{"->":".^.Start"},{"Start":["ev",{"CNT?":"Seth.Gruss"},"/ev",[{"->":".^.b","c":true},{"b":["^ ",{"->":"Seth.Hub"},{"->":".^.^.^.4"},null]}],"nop","\n",{"->":"Seth.Gruss"},{"#f":1}],"Gruss":[["^Seth: Ein herzliches willkommen, geschätzter Kunde. Es ist mir eine Freude deine Wünsche auf das Äusserste zu erfüllen. ","#","^Seth","/#","\n","^Seth: Du bist eingeladen dich in meinem <color=#58FF5E>Ladeny/color> zu verlieren und bis ans Ende der Zeit hier Geld zu lassen. ","#","^Seth","/#","\n","^Locus: Ja... Hallo erstmal... ","#","^Locus","/#","\n","^Seth: Bitte bitte, nicht so zurückhaltend. Ich habe meine <color=#66DBFF>neunköpfige Familie</color> zu ernähren. ","#","^Seth","/#","\n","ev","str","^Familie?","/str","/ev",{"*":".^.c-0","flg":20},"ev","str","^Kaufen?","/str","/ev",{"*":".^.c-1","flg":20},"ev","str","^Ballons","/str","/ev",{"*":".^.c-2","flg":20},{"c-0":[{"->":"Seth.Familie"},"\n",{"#f":5}],"c-1":[{"->":"Seth.Kaufen"},"\n",{"#f":5}],"c-2":["^ ",{"->":"Seth.Ballons"},"\n",{"#f":5}]}],{"#f":1}],"Familie":[["^Locus: Sagtest du <color=#66DBFF>achtköpfige Familie</color>? ","#","^Locus","/#","\n","^Seth: Ganz recht. Ich und meine Frau <color=#66DBFF>Clara Kopf</color> haben 7 wunderbare Kinder. ","#","^Seth","/#","\n","^Seth: Besonders stolz bin ich auf meine <color=#66DBFF>Charlocke</color>. Sie hat seit kurzen die Fühung eines <color=#58FF5E>Limonadenstandes</color> übernommen. ","#","^Seth","/#","\n","^Seth: Ich hoffe wenn ihr Schädel voll ausgewachsen ist, wird sie eines Tages meinen Laden übernehmen können. Das wäre mein Hirneswunsch. ","#","^Seth","/#","\n","^Seth: Wo wir gerade davon sprechen. Es wäre mir eine grosse Freude wenn du bei Gelegenheit meine ganze <color=#58FF5E>Familie einsammeln</color> könntest und sie her bringst. ","#","^Seth","/#","\n","^Locus: Sagtest du \"einsammeln\"? ","#","^Locus","/#","\n","^Seth: Ganz recht. Du läuft einfach über sie drüber und dann sollten sie sich in deinem Sack wiederfinden. ","#","^Seth","/#","\n","^Locus: Meinem Sack? ","#","^Locus","/#","\n","^Seth: Ach du weisst was ich meine! ","#","^Seth","/#","\n","ev","str","^Q-Skull-1","/str",{"x()":"Unity_Event","exArgs":1},"pop","/ev","\n","ev","str","^Kaufen?","/str","/ev",{"*":".^.c-0","flg":20},"ev","str","^Ballons","/str","/ev",{"*":".^.c-1","flg":4},{"c-0":[{"->":"Seth.Kaufen"},"\n",{"#f":5}],"c-1":["^ ",{"->":"Seth.Ballons"},"\n",{"#f":5}]}],{"#f":1}],"Kaufen":["^Locus: Wollen denn alle hier nur mein Geld? ","#","^Locus","/#","\n","^Seth: Aber aber mein Bester, das ist doch nur ein bescheidenes Handelsangebot. Mach dir doch erstmal ein Bild und besichtige meine Waren. ","#","^Seth","/#","\n","^Locus: Wenns denn sein muss. Was verkaufst du denn alles hier? ","#","^Locus","/#","\n","^Seth: Mein Angebot reicht von Parfums, über Bodylotions bis hin zu Büchern und Glaskugeln fürs Wahrsagen. Du scheinst mir aber nicht der übernatürliche Typ dafür zu sein. ","#","^Seth","/#","\n",{"->":"Seth.Weiter"},{"#f":1}],"Parfum":[["^Locus: Du verkaufst Parfums? ","#","^Locus","/#","\n","^Seth: Aber sicher und davon nicht zu knapp. Es ist wahre Privileg gut zu riechen, vor allem in diesem Höllenloch. ","#","^Seth","/#","\n","ev","str","^Nase ansprechen","/str","/ev",{"*":".^.c-0","flg":20},"ev","str","^nicht ansprechen","/str","/ev",{"*":".^.c-1","flg":20},{"c-0":[{"->":"Seth.Nase"},"\n",{"#f":5}],"c-1":[{"->":"Seth.Weiter"},"\n",{"#f":5}]}],{"#f":1}],"Nase":["^Locus: Wie kannst du denn riechen so ganz ohne Nase? ","#","^Locus","/#","\n","^Seth: Das ist ja eine absolute Frechheit! Immer diese Vorurteile! ","#","^Seth","/#","\n","^Seth: Ich erinnere mich noch sehr gut an meine Lebzeiten, in denen ich riechen konnte. Aber nun genug davon.","#","^Seth","/#","\n",{"->":"Seth.Weiter"},{"#f":1}],"Weiter":[["^Seth: ",["ev","visit",6,"%","/ev","ev","du",0,"==","/ev",{"->":".^.s0","c":true},"ev","du",1,"==","/ev",{"->":".^.s1","c":true},"ev","du",2,"==","/ev",{"->":".^.s2","c":true},"ev","du",3,"==","/ev",{"->":".^.s3","c":true},"ev","du",4,"==","/ev",{"->":".^.s4","c":true},"ev","du",5,"==","/ev",{"->":".^.s5","c":true},"nop",{"s0":["pop","^Wie kann ich weiterhelfen?",{"->":".^.^.41"},null],"s1":["pop","^Was willst du noch wissen?",{"->":".^.^.41"},null],"s2":["pop","^Wie kann ich weiter dienlich sein?",{"->":".^.^.41"},null],"s3":["pop","^Noch was?",{"->":".^.^.41"},null],"s4":["pop","^Weitere Fragen?",{"->":".^.^.41"},null],"s5":["pop","^Kann ich sonst noch etwas für dich tun?",{"->":".^.^.41"},null],"#f":5}],"\n","ev","str","^Parfums?","/str","/ev",{"*":".^.c-0","flg":20},"ev","str","^Bodylotions?","/str","/ev",{"*":".^.c-1","flg":20},"ev","str","^Bücher?","/str","/ev",{"*":".^.c-2","flg":20},"ev","str","^Glaskugeln?","/str","/ev",{"*":".^.c-3","flg":20},"ev","str","^Ballons","/str",{"CNT?":"Seth.Skelett"},"!","/ev",{"*":".^.c-4","flg":5},"ev","str","^Gehen","/str",{"CNT?":"Seth.Skelett"},"/ev",{"*":".^.c-5","flg":5},{"c-0":[{"->":"Seth.Parfum"},"\n",{"#f":5}],"c-1":[{"->":"Seth.Bodylotion"},"\n",{"#f":5}],"c-2":[{"->":"Seth.Buch"},"\n",{"#f":5}],"c-3":[{"->":"Seth.Glaskugeln"},"\n",{"#f":5}],"c-4":["^ ",{"->":"Seth.Ballons"},"\n",{"#f":5}],"c-5":["^ Locus: Ich mache mich dann mal auf deine bessere Hälfte zu finden.. oder Dreiviertel oder so. ","#","^Locus","/#","\n","end",{"#f":5}]}],{"#f":1}],"Bodylotion":[["^Locus: Wieso verkaufst du Bodylotion? Wie kommt man dazu so etwas zu verkaufen, so als Kopf... ","#","^Locus","/#","\n","^Seth: Ach weisst du früher hatte ich einmal einen wirklich <color=#58FF5E>strammen Körper</color>. Mit Armen und Beinen. ","#","^Seth","/#","\n","^Seth: Doch habe ich eines schlimmen Tages, einfach den Kopf verloren oder viel mehr meinen <color=#58FF5E>Körper</color>. ","#","^Seth","/#","\n","^Seth: Ich würde alles dafür geben wieder mein <color=#58FF5E>Skelett</color> zu haben. Und was erst meine Frau <color=#66DBFF>Clara</color> dazu sagen würde... ","#","^Seth","/#","\n","ev","str","^Helfen","/str","/ev",{"*":".^.c-0","flg":20},"ev","str","^Weiter","/str","/ev",{"*":".^.c-1","flg":20},{"c-0":["^ ",{"->":"Seth.Skelett"},"\n",{"#f":5}],"c-1":["^ ",{"->":"Seth.Weiter"},"\n",{"#f":5}]}],{"#f":1}],"Skelett":["^Locus: Ich kann versuchen deinen <color=#58FF5E>Körper</color> zu finden. ","#","^Locus","/#","\n","^Seth: Ich danke dir. Solltest du meinen <color=#58FF5E>Körper</color> wirklich finden, gebe ich dir einen höllischen Rabatt auf meine Preise! ","#","^Seth","/#","\n","^Locus: Ich wäre wohl mehr an deinen <color=#58FF5E>Ballons</color> interessiert. ","#","^Locus","/#","\n","^Seth: Aber sicher, die brauche ich auch nicht mehr nachdem ich wieder auf eigenen Beinen stehen kann. ","#","^Seth","/#","\n","ev","str","^Q-Seth-1","/str",{"x()":"Unity_Event","exArgs":1},"pop","/ev","\n",{"->":"Seth.Weiter"},{"#f":1}],"Buch":["^Locus: Du verkaufst also auch Bücher? ","#","^Locus","/#","\n","^Seth: Gewiss. Du wirst alles von Nekomantie bis hin zu Keksrezepten hier finden. Hast du ein spezielles Interesse?","#","^Seth","/#","\n","^Locus: Hast du Bilderbücher? ","#","^Locus","/#","\n","^Seth: Bilderbücher? Wie alt bist du? Vier? ","#","^Seth","/#","\n","^Locus: Ach vergiss es! ","#","^Locus","/#","\n",{"->":"Seth.Weiter"},{"#f":1}],"Glaskugeln":["^Locus: Wer kauft denn Glaskugeln? ","#","^Locus","/#","\n","^Seth: Die verkaufe ich hautsächlich an die alten Schreckschrauben vom Bridgeclub. Die meinen alle damit können sie die Karten ihrer Kontrahenten einsehen. ","#","^Seth","/#","\n","^Seth: Kleines Geheimnis am Rande, alle meine <color=#58FF5E>Glaskugeln sind batteriebetrieben</color>. ","#","^Seth","/#","\n","^Seth: Da diese Hexen das nicht wissen kommen sie alle paar Wochen wieder. Sie denken der Geist der Kugel hätte sie wegen ihrer schändlichen Taten verlassen. ","#","^Seth","/#","\n","^Seth: Das ist mein Topseller. In der Businesswelt braucht man eben Köpfchen. ","#","/#","#","^Seth","/#","\n",{"->":"Seth.Weiter"},{"#f":1}],"Ballons":["^Locus: Stehen deine <color=#58FF5E>Ballons</color> auch zum Verkauf? ","#","^Locus","/#","\n","^Seth: Nein, tut mir leid. Ich benötige diese um mit meinen Kunden auf Augenhöhe zu verhandeln. ","#","^Seth","/#","\n","^Seth: Das ist eine Priorität für einen jeden Geschäftsmann. ","#","^Seth","/#","\n",{"->":"Seth.Skelett"},{"#f":1}],"Hub":[["^Seth: ",["ev","visit",4,"%","/ev","ev","du",0,"==","/ev",{"->":".^.s0","c":true},"ev","du",1,"==","/ev",{"->":".^.s1","c":true},"ev","du",2,"==","/ev",{"->":".^.s2","c":true},"ev","du",3,"==","/ev",{"->":".^.s3","c":true},"nop",{"s0":["pop","^Und? Hast du Neuigkeiten?",{"->":".^.^.29"},null],"s1":["pop","^Gibt es etwas Neues?",{"->":".^.^.29"},null],"s2":["pop","^Willkommen zurück! Hast du Informationen für mich?",{"->":".^.^.29"},null],"s3":["pop","^ Locus! Weisst du schon mehr?",{"->":".^.^.29"},null],"#f":5}],"^ ","#","^Seth","/#","\n","ev","str","^Skelett","/str","str","^item_skelett","/str",{"x()":"Get_State","exArgs":1},"/ev",{"*":".^.c-0","flg":21},"ev","str","^Skelett","/str","str","^item_skull = 8","/str",{"x()":"Get_State","exArgs":1},{"CNT?":"Seth.Familie"},"&&","/ev",{"*":".^.c-1","flg":21},"ev","str","^Nein","/str","/ev",{"*":".^.c-2","flg":4},{"c-0":[{"->":"Seth.Skelend"},"\n",{"#f":5}],"c-1":[{"->":"Seth.Kopfend"},"\n",{"#f":5}],"c-2":["^ Locus: Ich arbeite daran. Lass den Kopf nicht hängen. ","#","^Locus","/#","\n","end",{"#f":5}]}],{"#f":1}],"Skelend":["^Seth: Du hast ihn wahrhaftig gefunden, meinen alten <color=#58FF5E>Körper</color>! Welch ein wunderbares wiedersehen! Mach die Augen zu, ich werde mich nun umziehen! ","#","^Seth","/#","\n","ev","str","^Q-Seth-3","/str",{"x()":"Unity_Event","exArgs":1},"pop","/ev","\n","ev","str","^item_skelett","/str",-1,{"x()":"Add_State","exArgs":2},"pop","/ev","\n","^Seth: Du hast ihn wahrhaftig gefunden, meinen alten <color=#58FF5E>Körper</color>! Welch ein wunderbares wiedersehen! Mach die Augen zu, ich werde mich nun umziehen!","\n","^Seth: Er passt noch wie zu meinen Glanzzeiten! Ich hätte solch ein Glücksgefühl hier unten nicht für möglich gehalten. ","#","^Seth","/#","\n","^Seth: Und wenn erst der <color=#66DBFF>Meister</color> das sieht, wir er mir sicher auch die Expansion in den Limbo gestatten. ","#","^Seth","/#","\n","^Locus: Was ist nun mit den <color=#58FF5E>Ballons</color>? ","#","^Locus","/#","\n","^Seth: Achja, die Ballons. Die brauche ich nun nicht mehr. Nie mehr! Bitte nimm sie. ","#","^Seth","/#","\n","ev","str","^item_ballons","/str",1,{"x()":"Add_State","exArgs":2},"pop","/ev","\n","^Locus: Eine Freude mit dir Geschäfte zu machen. ","#","^Locus","/#","\n","end",{"#f":1}],"Kopfend":[["^Locus: Ich habe nun deine ganze Familie beisammen. ","#","^Locus","/#","\n","^Seth: Oh du bist mir ein Quell der Freude. Es ist eine Zeit her seit dem letzten Familientreffen. ","#","^Seth","/#","\n","ev","str","^Q-Skull-2","/str",{"x()":"Unity_Event","exArgs":1},"pop","/ev","\n","^Locus: Bekomme ich nun Kopf-Geld? ","#","^Locus","/#","\n","^Seth: Wie? Hast du das denn nicht aus Nächstenliebe gemacht? Oder um einem Freund und seiner Familie zu helfen?","\n","ev","str","^Doch","/str","/ev",{"*":".^.c-0","flg":20},"ev","str","^Nein","/str","/ev",{"*":".^.c-1","flg":20},{"c-0":[{"->":"Seth.Nix"},"\n",{"#f":5}],"c-1":[{"->":"Seth.Lohn"},"\n",{"#f":5}]}],{"#f":1}],"Nix":["^Locus: Das war selbstverständlich nur ein kleiner Witz. Es freut mich, dass du mit deine Familie wieder vereint bist. ","#","^Locus","/#","\n","^Seth: Ich werde es dir nicht vergessen. ","#","^Seth","/#","\n","end",{"#f":1}],"Lohn":[["^Locus: Nein, ich will für meine Abrbeit bezahlt werden! ","#","^Locus","/#","\n","^Seth: Das kann ich verstehe aber ich bekomme auch nicht immer was ich will. Ich habe selbst fast nichts! ","#","^Seth","/#","\n","^Seth: Aber ich will mal nicht so sein. Gut ich werde dir eine <color=#58FF5E>Glaskugel</color> zu deinem Bereich liefern lassen. ","#","^Seth","/#","\n","ev","str","^Mit Batterien","/str",{"CNT?":"Seth.Glaskugeln"},"/ev",{"*":".^.c-0","flg":21},"ev","str","^Lieber nicht","/str","/ev",{"*":".^.c-1","flg":20},"ev","str","^Danke","/str","/ev",{"*":".^.c-2","flg":20},{"c-0":[{"->":"Seth.KugelB"},"\n",{"#f":5}],"c-1":[{"->":"Seth.Keinekugel"},"\n",{"#f":5}],"c-2":[{"->":"Seth.KugelA"},"\n",{"#f":5}]}],{"#f":1}],"KugelB":["^Locus: Ich will aber auch ausreichend <color=#58FF5E>Batterien</color> dazu und mir nicht direkt eine neue kaufen müssen. ","#","^Locus","/#","\n","^Seth: Aber sicher doch, selbstreden für eine solche Tat bekommst du auch genug Batterien. ","#","^Seth","/#","\n","ev","str","^Kugel","/str",{"x()":"Unity_Event","exArgs":1},"pop","/ev","\n","^Locus: Wunderbar, ein guter Deal!","\n","end",{"#f":1}],"Keinekugel":["^Locus: Nein danke, dann nehme ich lieber nichts. Ich möchten keinen Hokuspokus. ","#","^Locus","/#","\n","^Seth: Ganz wie du willst. Trotzdem danke. Beehre uns bald wieder. ","#","^Seth","/#","\n","end",{"#f":1}],"KugelA":["^Locus: Na geht doch. Ein guter Deal. ","#","^Locus","/#","\n","^Seth: Aber sicher doch und solltest du die Kugel verärgern, bist du eingeladen dir eine neue zu kaufen. ","#","^Seth","/#","\n","^Locus: Wieso sollte sie verärgert sein? ","#","^Locus","/#","\n","ev","str","^Kugel","/str",{"x()":"Unity_Event","exArgs":1},"pop","/ev","\n","^Seth: Das ist ein Betriebsgeheimnis. Ich danke aber für deine Hilfe. ","#","^Seth","/#","\n","end",{"#f":1}],"#f":1}],"Rasmus":[{"->":".^.Start"},{"Start":["ev",{"CNT?":".^.^.Sage2"},"/ev",[{"->":".^.b","c":true},{"b":["^ ",{"->":"Rasmus.PostSage"},{"->":".^.^.^.4"},null]}],"nop","\n","ev",{"CNT?":".^.^.Instrumente"},"/ev",[{"->":".^.b","c":true},{"b":["^ ",{"->":"Rasmus.PostAnzeige"},{"->":".^.^.^.10"},null]}],"nop","\n","ev",{"CNT?":".^.^.Zahlen5"},"/ev",[{"->":".^.b","c":true},{"b":["^ ",{"->":"Rasmus.PostBett"},{"->":".^.^.^.16"},null]}],"nop","\n","ev",{"CNT?":".^.^.5B"},"/ev",[{"->":".^.b","c":true},{"b":["^ ",{"->":"Rasmus.Sage"},{"->":".^.^.^.22"},null]}],"nop","\n","ev",{"CNT?":".^.^.Zahlen32"},"/ev",[{"->":".^.b","c":true},{"b":["^ ",{"->":"Rasmus.Sage"},{"->":".^.^.^.28"},null]}],"nop","\n","ev",{"CNT?":".^.^.Gruss"},"/ev",[{"->":".^.b","c":true},{"b":["^ ",{"->":"Rasmus.Back"},{"->":".^.^.^.34"},null]}],"nop","\n",{"->":".^.^.Gruss"},{"#f":1}],"Gruss":[["^Rasmus: <color=#66DBFF>Locus>/color>... ","#","^Rasmus","/#","\n","^Locus: Hallo <color=#66DBFF>Rasmus</color>, wie läuft die <color=#58FF5E>Ernte</color>? ","#","^Rasmus","/#","\n","^Rasmus: Nun seit dem du mir nicht mehr in meine Arbeit funkst oder mich sabotiertst läuft es ausgesprochen gut. ","#","^Rasmus","/#","\n","^Locus: Ach was, ich glaube eher du hast Probleme, bist überarbeitet aber willst das vor mir nicht zugeben. ","#","^Locus","/#","\n","^Rasmus: Überzeug dich selbst. Die <color=#58FF5E>Tränenernte</color> dieses Monats fiel sehr gut aus. Sie ist wohl eine der besten seit langem. ","#","^Rasmus","/#","\n","ev","str","^Meine Vorarbeit","/str","/ev",{"*":".^.c-0","flg":20},"ev","str","^Glück","/str","/ev",{"*":".^.c-1","flg":20},{"c-0":[{"->":"Rasmus.Vorarbeit"},"\n",{"#f":5}],"c-1":[{"->":"Rasmus.Gluck"},"\n",{"#f":5}]}],{"#f":1}],"Vorarbeit":["^Locus: Das kommt natürlich alles von meiner unermüdlichen Vorarbeit. Leider haben das gewisse andere Leute nicht zu schätzen gewusst. ","#","^Locus","/#","\n",{"->":".^.^.Herausforderung"},{"#f":1}],"Gluck":["^Locus: Das ist selbstverständlich nur Glück! Ich denke aber nicht, dass das noch lange von Dauer sein wird. ","#","^Locus","/#","\n",{"->":".^.^.Herausforderung"},{"#f":1}],"Herausforderung":[["^Rasmus: Rede dir das nur weiter ein. Ich bin überzeugt, dass ich ohne dich weit mehr Tränen ernte. ","#","^Rasmus","/#","\n","ev","str","^Tränen für Fest?","/str","/ev",{"*":".^.c-0","flg":20},"ev","str","^Gehen","/str","/ev",{"*":".^.c-1","flg":4},{"c-0":["^ ",{"->":"Rasmus.Feste"},"\n",{"#f":5}],"c-1":["^ Locus: Na dann, ernte mal schön weiter so allein! ","#","^Locus","/#","\n","end",{"#f":5}]}],{"#f":1}],"Back":[["^Rasmus: Was willst du <color=#66DBFF>Locus</color>? ","#","^Rasmus","/#","\n","ev","str","^Tränen für Fest?","/str","/ev",{"*":".^.c-0","flg":20},"ev","str","^Gehen","/str","/ev",{"*":".^.c-1","flg":4},{"c-0":["^ ",{"->":"Rasmus.Feste"},"\n",{"#f":5}],"c-1":["^ Locus: Ach nichts, ich habe mich nur verklickt. ","#","^Locus","/#","\n","end",{"#f":5}]}],{"#f":1}],"Feste":[["^Locus: Denkst du der <color=#66DBFF>Meister</color> mag <color=#58FF5E>Tränen</color>? ","#","^Locus","/#","\n","^Rasmus: Sicherlich. Der <color=#58FF5E>Jahrgang 2013</color> wird von ihm bevorzugt. Davon habe ich nur noch <color=#58FF5E>zwei Flaschen</color> in der Reserve. ","#","^Rasmus","/#","\n","ev","str","^Q-Rasmus-1","/str",{"x()":"Unity_Event","exArgs":1},"pop","/ev","\n","^Locus: Wäre es möglich, dass ich eine dieser <color=#58FF5E>Flaschen</color> bekomme? ","#","^Locus","/#","\n","^Rasmus: Meinst du das ernst? Ich soll dir eine der wertvollsten <color=#58FF5E>Flaschen</color> meines Lagers geben? ","#","^Rasmus","/#","\n","^Locus: Es ist für unseren <color=#66DBFF>Meister den Teufel</color>. Ist dir das nicht Grund genug? ","#","^Locus","/#","\n","^Rasmus: Nein ist es nicht. Ich bin überzeugt, dass der <color=#66DBFF>Teufel</color> dich dafür bestafen wird wenn er nicht bekommt was er will. ","#","^Rasmus","/#","\n","ev","str","^Bitten","/str","/ev",{"*":".^.c-0","flg":20},"ev","str","^Bezahlen?","/str","/ev",{"*":".^.c-1","flg":20},"ev","str","^Helfen","/str","/ev",{"*":".^.c-2","flg":20},"ev","str","^Drohen","/str","/ev",{"*":".^.c-3","flg":20},{"c-0":["^ ",{"->":"Rasmus.Bitte"},"\n",{"#f":5}],"c-1":[{"->":"Rasmus.Zahlen"},"\n",{"#f":5}],"c-2":[{"->":"Rasmus.Help"},"\n",{"#f":5}],"c-3":[{"->":"Rasmus.Droh"},"\n",{"#f":5}]}],{"#f":1}],"Hub":[["^Locus: Ich sollte etwas anderes versuchen. ","#","^thought","/#","\n","ev","str","^Bitten","/str",{"CNT?":"Rasmus.Bitte"},"!","/ev",{"*":".^.c-0","flg":21},"ev","str","^Bezahlen?","/str",{"CNT?":"Rasmus.Zahlen"},"!","/ev",{"*":".^.c-1","flg":21},"ev","str","^Helfen","/str","/ev",{"*":".^.c-2","flg":4},"ev","str","^Drohen","/str",{"CNT?":"Rasmus.Droh"},"!","/ev",{"*":".^.c-3","flg":21},{"c-0":["^ ",{"->":"Rasmus.Bitte"},"\n",{"#f":5}],"c-1":[{"->":"Rasmus.Zahlen"},"\n",{"#f":5}],"c-2":[{"->":"Rasmus.Help"},"\n",{"#f":5}],"c-3":[{"->":"Rasmus.Droh"},"\n",{"#f":5}]}],{"#f":1}],"Bitte":[["^Locus: Darf ich es bitte haben? ","#","^Locus","/#","\n","^Rasmus: Was? Nein! ","#","^Rasmus","/#","\n","ev","str","^Bitte?","/str","/ev",{"*":".^.c-0","flg":20},"ev","str","^Zurück","/str","/ev",{"*":".^.c-1","flg":20},{"c-0":["^ ",{"->":"Rasmus.BitteBitte"},"\n",{"#f":5}],"c-1":[{"->":"Rasmus.Hub"},"\n",{"#f":5}]}],{"#f":1}],"BitteBitte":[["^Locus: Darf ich es bitte bitte haben? ","#","^Locus","/#","\n","^Rasmus: Denkst du so wirst du mich überzeugen? ","#","^Rasmus","/#","\n","ev","str","^Bitte?","/str","/ev",{"*":".^.c-0","flg":20},"ev","str","^Zurück","/str","/ev",{"*":".^.c-1","flg":20},{"c-0":["^ ",{"->":"Rasmus.BitteBitteBitte"},"\n",{"#f":5}],"c-1":[{"->":"Rasmus.Hub"},"\n",{"#f":5}]}],{"#f":1}],"BitteBitteBitte":[["^Locus: Bitte bitte bitte? ","#","^Locus","/#","\n","^Rasmus: Nein! ","#","^RasmusW","/#","\n","ev","str","^Bitte?","/str","/ev",{"*":".^.c-0","flg":20},"ev","str","^Zurück","/str","/ev",{"*":".^.c-1","flg":20},{"c-0":["^ ",{"->":"Rasmus.4B"},"\n",{"#f":5}],"c-1":[{"->":"Rasmus.Hub"},"\n",{"#f":5}]}],{"#f":1}],"4B":[["^Locus: Bitte bitte bitte Brigitte bitte bitte bitte? ","#","^Locus","/#","\n","^Rasmus: N E I N! ","#","^RasmusW","/#","\n","ev","str","^Bitte?","/str","/ev",{"*":".^.c-0","flg":20},"ev","str","^Zurück","/str","/ev",{"*":".^.c-1","flg":20},{"c-0":["^ ",{"->":"Rasmus.5B"},"\n",{"#f":5}],"c-1":[{"->":"Rasmus.Hub"},"\n",{"#f":5}]}],{"#f":1}],"5B":["^Locus: Bitte bitte bitte bitte bitte bitte bitte? ","#","^Locus","/#","\n","^Rasmus: GENUG! Ich sage dir was wir jetzt machen. Ich gebe dir die <color=#58FF5E>Flasche</color> wenn du mir von <color=#58FF5E>Kevins Schmiede</color> meine <color=#58FF5E>Säge</color> holst. Dann kann ich das wenigstens mit meinem Gewissen vereinbaren. ","#","^Rasmus","/#","\n","ev","str","^Q-Rasmus-2","/str",{"x()":"Unity_Event","exArgs":1},"pop","/ev","\n","^Locus: Danke danke danke danke danke danke danke danke! ","#","^Locus","/#","\n","^Rasmus: GEH JETZT! ","#","^RasmusW","/#","\n","end",{"#f":1}],"Zahlen":[["^Locus: Würdest du es mir verkaufen? ","#","^Locus","/#","\n","^Rasmus: Verkaufen? Dieser Idee bin ich nicht vollkommen abgeneigt. Was könntest du mir denn für die <color=#58FF5E>Flasche</color> geben? ","#","^Rasmus","/#","\n","ev","str","^Nichts","/str","/ev",{"*":".^.c-0","flg":20},"ev","str","^Freundschaft","/str","/ev",{"*":".^.c-1","flg":20},"ev","str","^Schal","/str",{"CNT?":"Remus.getSchal"},"/ev",{"*":".^.c-2","flg":21},"ev","str","^Halbfertiges Kreuzworträtsel","/str","/ev",{"*":".^.c-3","flg":20},"ev","str","^Mein Bett","/str","/ev",{"*":".^.c-4","flg":20},{"c-0":[{"->":"Rasmus.Zahlen1"},"\n",{"#f":5}],"c-1":[{"->":"Rasmus.Zahlen2"},"\n",{"#f":5}],"c-2":[{"->":"Rasmus.Zahlen3"},"\n",{"#f":5}],"c-3":[{"->":"Rasmus.Zahlen4"},"\n",{"#f":5}],"c-4":[{"->":"Rasmus.Zahlen5"},"\n",{"#f":5}]}],{"#f":1}],"Zahlen1":["^Locus: Gute 10 Kilogramm Luft in einem durchsichtigen Gefäss ohne Deckel oder Boden. ","#","^Locus","/#","\n","^Rasmus: Sehr witzig. Dann also nicht! Ich hatte kurz wirklich die Hoffnung, du hättest eine gute Idee und wir könnten uns einig werden. ","#","^Rasmus","/#","\n",{"->":".^.^.Hub"},{"#f":1}],"Zahlen2":[["^Locus: Eine langanhaltende und nicht durch Hintergedanken belastete, vitale Freundschaft? ","#","^Locus","/#","\n","^Rasmus: Ich denke dafür könnte es etwas zu spät sein. Hast du sonst noch etwas anzubieten?","#","^Rasmus","/#","\n","ev","str","^Nichts","/str","/ev",{"*":".^.c-0","flg":20},"ev","str","^Schal","/str",{"CNT?":"Remus.getSchal"},{"CNT?":"Rasmus.Zahlen3"},"!","&&","/ev",{"*":".^.c-1","flg":21},"ev","str","^Halbfertiges Kreuzworträtsel","/str",{"CNT?":"Rasmus.Zahlen4"},"!","/ev",{"*":".^.c-2","flg":21},"ev","str","^Mein Bett","/str","/ev",{"*":".^.c-3","flg":20},{"c-0":[{"->":"Rasmus.Zahlen1"},"\n",{"#f":5}],"c-1":[{"->":"Rasmus.Zahlen3"},"\n",{"#f":5}],"c-2":[{"->":"Rasmus.Zahlen4"},"\n",{"#f":5}],"c-3":[{"->":"Rasmus.Zahlen5"},"\n",{"#f":5}]}],{"#f":1}],"Zahlen3":[["^Locus: Einen wollig warmer <color=#58FF5E>Schal</color> für die kalten Tage des Jahres. ","#","^Locus","/#","\n","^Rasmus: Wir sind in der Hölle. Die kalten Tage lassen sich hier nicht wirklich sehen. Wie soll ich den <color=#58FF5E>Schal</color> sonst nutzen? ","#","^Rasmus","/#","\n","ev","str","^Stirnband?","/str","/ev",{"*":".^.c-0","flg":20},"ev","str","^Ernteinstrument?","/str","/ev",{"*":".^.c-1","flg":20},"ev","str","^Gürtel?","/str","/ev",{"*":".^.c-2","flg":20},{"c-0":[{"->":"Rasmus.Zahlen31"},"\n",{"#f":5}],"c-1":[{"->":"Rasmus.Zahlen32"},"\n",{"#f":5}],"c-2":[{"->":"Rasmus.Zahlen31"},"\n",{"#f":5}]}],{"#f":1}],"Zahlen31":[["^Locus: Als modisches Accessoir um deine Überlegenheit zu zeigen. ","#","^Locus","/#","\n","^Rasmus: Nein, ich denke nicht, dass das zu mir passt oder funktioniert. Ich möchte den Schal nicht. Hast du sonst noch etwas anzubieten?","#","^Rasmus","/#","\n","ev","str","^Nichts","/str","/ev",{"*":".^.c-0","flg":20},"ev","str","^Freundschaft","/str",{"CNT?":"Rasmus.Zahlen2"},"!","/ev",{"*":".^.c-1","flg":21},"ev","str","^Halbfertiges Kreuzworträtsel","/str",{"CNT?":"Rasmus.Zahlen4"},"!","/ev",{"*":".^.c-2","flg":21},"ev","str","^Mein Bett","/str","/ev",{"*":".^.c-3","flg":20},{"c-0":[{"->":"Rasmus.Zahlen1"},"\n",{"#f":5}],"c-1":[{"->":"Rasmus.Zahlen2"},"\n",{"#f":5}],"c-2":[{"->":"Rasmus.Zahlen4"},"\n",{"#f":5}],"c-3":[{"->":"Rasmus.Zahlen5"},"\n",{"#f":5}]}],{"#f":1}],"Zahlen32":["^Locus: Als neues Instrument für die <color=#58FF5E>Tränenernte</color> um nächsten Monat deine Erträge zu steigern. ","#","^Locus","/#","\n","^Rasmus: Hmmm... Ja das könnte funktionieren. Ich nehme den Schal, aber das reicht mir noch nicht. Ich weiss auch schon was. ","#","^Rasmus","/#","\n","^Rasmus: Um mein Satz an <color=#58FF5E>Ernteinstrumenten</color> nochmals zu erweitern, gehe zu <color=#66DBFF>Kevin</color> und hol mir meine <color=#58FF5E>Säge</color> zurück.","\n","ev","str","^Q-RasmusB-2","/str",{"x()":"Unity_Event","exArgs":1},"pop","/ev","\n","ev","str","^item_schal","/str",-1,{"x()":"Add_State","exArgs":2},"pop","/ev","\n","^Locus: Bekomme ich dafür auch beide <color=#58FF5E>Flaschen</color>? ","#","^Locus","/#","\n","^Rasmus: Nein, du bekommst eine <color=#58FF5E>Flasche</color> und das ist schon viel zu grosszügig. ","#","^Rasmus","/#","\n","end",{"#f":1}],"Zahlen4":[["^Locus: Ein halbfertiges Kreuzworträtsel von vor zwei Wochen? ","#","^Locus","/#","\n","^Rasmus: Wie kommst du darauf, dass ich sowas wollen würde? ","#","^Rasmus","/#","\n","^Locus: Ich habe gehört, dass die meisten alten, griesgrämigen Leute sowas mögen. ","#","^Locus","/#","\n","^Rasmus: Damit kriegst du mich nicht. Hast du sonst noch etwas anzubieten? ","#","^Rasmus","/#","\n","ev","str","^Nichts","/str","/ev",{"*":".^.c-0","flg":20},"ev","str","^Freundschaft","/str",{"CNT?":"Rasmus.Zahlen2"},"!","/ev",{"*":".^.c-1","flg":21},"ev","str","^Schal","/str",{"CNT?":"Remus.getSchal"},{"CNT?":"Rasmus.Zahlen3"},"!","&&","/ev",{"*":".^.c-2","flg":21},"ev","str","^Mein Bett","/str","/ev",{"*":".^.c-3","flg":20},{"c-0":[{"->":"Rasmus.Zahlen1"},"\n",{"#f":5}],"c-1":[{"->":"Rasmus.Zahlen2"},"\n",{"#f":5}],"c-2":[{"->":"Rasmus.Zahlen3"},"\n",{"#f":5}],"c-3":[{"->":"Rasmus.Zahlen5"},"\n",{"#f":5}]}],{"#f":1}],"Zahlen5":["^Locus: Es schmerzt mich das anzubieten, aber ich sehe du hast ausser deiner Streckbank keine Schlafmöglichkeit. ich könnte dir im Tausch mein <color=#58FF5E>Bett</color> anbieten. ","#","^Locus","/#","\n","^Rasmus: Ein <color=#58FF5E>Bett</color>? Das wäre wirklich eine schöne Ergänzung für mein Abteil. Sowas in der Art hat mir auch schon mein Innenarchitekt geraten. ","#","^Rasmus","/#","\n","^Rasmus: Also gut, ich tasuche dein <color=#58FF5E>Bett</color> gegen eine <color=#58FF5E>Flasche</color>. Ich werde es sogleich holen lassen.","#","^Rasmus","/#","\n","ev","str","^Q-RasmusC-3","/str",{"x()":"Unity_Event","exArgs":1},"pop","/ev","\n","ev","str","^item_flasche","/str",1,{"x()":"Add_State","exArgs":2},"pop","/ev","\n","^Locus: Danke.. denke ich.. ","#","^Locus","/#","\n","end",{"#f":1}],"Help":["^Locus: Kann ich dir vielleicht bei der <color=#58FF5E>Tränenernte</color> helfen? ","#","^Locus","/#","\n","^Rasmus: Nein bitte nur das nicht! ... Ich habe aber eine andere Idee wie du dir die <color=#58FF5E>Flasche</color> verdienen kannst. Ich habe vor kurzem <color=#66DBFF>Kevin</color> meine <color=#58FF5E>Säge</color> geliehen weil er sich ein Bett machen wollte oder sowas.","\n","^Rasmus: Hol mir die <color=#58FF5E>Säge</color> zurück und versprich mir, dass du mich nie wieder belästigst. Dann überlasse ich dir eine Flasche. ","#","^Rasmus","/#","\n","^Locus: Ich verspreche es. ","#","^Locus","/#","\n","ev","str","^Q-Rasmus-2","/str",{"x()":"Unity_Event","exArgs":1},"pop","/ev","\n","^Rasmus: Gut, dann mol mir mein <color=#58FF5E>Ernteinstrument</color>. ","#","^Rasmus","/#","\n","end",{"#f":1}],"Droh":[["^Locus: Gib mir mir sofort die <color=#58FF5E>Flasche</color> oder ich... ","#","^Locus","/#","\n","ev","str","^Schlagen","/str","/ev",{"*":".^.c-0","flg":20},"ev","str","^Anzeigen","/str","/ev",{"*":".^.c-1","flg":20},{"c-0":[{"->":"Rasmus.Schlagen"},"\n",{"#f":5}],"c-1":[{"->":"Rasmus.Anzeigen"},"\n",{"#f":5}]}],{"#f":1}],"Schlagen":["^Locus: Gib mir mir sofort die <color=#58FF5E>Flasche</color> oder ich werde dich schlagen! ","#","^Locus","/#","\n","^Rasmus: Aber sicher doch. Ich kenne dich <color=#66DBFF>Locus</color>, du würdest verlieren, versuch es also gar nicht erst! ","#","^Rasmus","/#","\n",{"->":".^.^.Hub"},{"#f":1}],"Anzeigen":[["^Locus: Gib mir mir sofort die <color=#58FF5E>Flasche</color> oder ich zeig dich an! ","#","^Locus","/#","\n","^Rasmus: Wieso willst du micht denn anzeigen? ","#","^Rasmus","/#","\n","ev","str","^Lärmbelästigung","/str","/ev",{"*":".^.c-0","flg":20},"ev","str","^Ernteinstrumente","/str","/ev",{"*":".^.c-1","flg":20},{"c-0":[{"->":"Rasmus.Laut"},"\n",{"#f":5}],"c-1":[{"->":"Rasmus.Instrumente"},"\n",{"#f":5}]}],{"#f":1}],"Laut":["^Locus: Die Schreie deiner Patienten sind viel zu laut zur nächtlichen Ruhezeit! ","#","^Locus","/#","\n","^Rasmus: Ich denke nicht, dass dir das etwas bringen wird. ","#","^Rasmus","/#","\n",{"->":".^.^.Hub"},{"#f":1}],"Instrumente":["^Locus: Ich habe gesehen, dass die <color=#58FF5E>Lizenz deiner Streckbank</color> ausgelaufgen ist. Ich werde das <color=#66DBFF>Remus</color> melden müssen. ","#","^Locus","/#","\n","^Rasmus: Was? Ich.. also..  Das wollte ich gerade heute austauschen. ","#","^Rasmus","/#","\n","^Locus: Erzähl das dem Richter! ","#","^Locus","/#","\n","^Rasmus: Nagut. Ich überlasse dir eine <color=#58FF5E>Flasche</color> aber sag bloss nichts weiter!","\n","ev","str","^Q-RasmusD-3","/str",{"x()":"Unity_Event","exArgs":1},"pop","/ev","\n","ev","str","^item_flasche","/str",1,{"x()":"Add_State","exArgs":2},"pop","/ev","\n","^Locus: Na geht doch. Keine Sorge die Sache ist schon vergessen. ","#","^Locus","/#","\n","end",{"#f":1}],"Sage":[["^Rasmus: Hast du die <color=#58FF5E>Säge</color> schon? ","#","^Rasmus","/#","\n","ev","str","^Noch nicht","/str","/ev",{"*":".^.c-0","flg":4},"ev","str","^Säge geben","/str","str","^item_sage","/str",{"x()":"Get_State","exArgs":1},"/ev",{"*":".^.c-1","flg":21},{"c-0":["^ Locus: Noch nicht, ich werde mich schon bald darum kümmern. ","#","^locus","/#","\n","end",{"#f":5}],"c-1":[{"->":"Rasmus.Sage2"},"\n",{"#f":5}]}],{"#f":1}],"Sage2":["^Locus: Hier hast du deine <color=#58FF5E>Säge</color>. Bekomme ich nun meine <color=#58FF5E>Flasche</color>? ","#","^Locus","/#","\n","^Rasmus: Hier hast du die <color=#58FF5E>Flasche</color>, du Flasche! ","#","^Rasmus","/#","\n","ev","str","^Q-Rasmus-3","/str",{"x()":"Unity_Event","exArgs":1},"pop","/ev","\n","ev","str","^item_flasche","/str",1,{"x()":"Add_State","exArgs":2},"pop","/ev","\n","^Locus: Es war auch mir eine Freude mit dir Geschäfte zu machen. ","#","^Locsu","/#","\n","end",{"#f":1}],"PostSage":["^Rasmus: Stör mich nun nicht weiter! ","#","^Rasmus","/#","\n","end",{"#f":1}],"PostBett":["^Rasmus: ",["ev","visit",1,"MIN","/ev","ev","du",0,"==","/ev",{"->":".^.s0","c":true},"ev","du",1,"==","/ev",{"->":".^.s1","c":true},"nop",{"s0":["pop","^Danke nochmals für das Bett. Ich hoffe du bereust das nicht. Falls du dann noch einen Platz zum schlafen suchst, wir haben beim Lavasee noch eine Brücke für dich.",{"->":".^.^.17"},null],"s1":["pop","^Stör mich nun nicht weiter!",{"->":".^.^.17"},null],"#f":5}],"^ ","#","^Rasmus","/#","\n","end",{"#f":1}],"PostAnzeige":["^Rasmus: ",["ev","visit",1,"MIN","/ev","ev","du",0,"==","/ev",{"->":".^.s0","c":true},"ev","du",1,"==","/ev",{"->":".^.s1","c":true},"nop",{"s0":["pop","^Diese Erpressung war wiklich kein sehr ehrenvoller Zug von dir.",{"->":".^.^.17"},null],"s1":["pop","^Stör mich nun nicht wieter!",{"->":".^.^.17"},null],"#f":5}],"^ ","#","^Rasmus","/#","\n","end",{"#f":1}],"#f":1}],"Magister":[{"->":".^.Start"},{"Start":["ev",{"CNT?":".^.^.getKuchen"},"/ev",[{"->":".^.b","c":true},{"b":["^ ",{"->":"Magister.PostMagister"},{"->":".^.^.^.4"},null]}],"nop","\n","ev",{"CNT?":".^.^.Auftrag"},"/ev",[{"->":".^.b","c":true},{"b":["^ ",{"->":"Magister.PreBeginn"},{"->":".^.^.^.10"},null]}],"nop","\n","ev",{"CNT?":".^.^.Gruss"},"/ev",[{"->":".^.b","c":true},{"b":["^ ",{"->":"Magister.Back"},{"->":".^.^.^.16"},null]}],"nop","\n",{"->":".^.^.Gruss"},{"#f":1}],"Gruss":[["^Magister: Ah <color=#66DBFF>Locus</color>, welch eine Überraschung. ","#","^Magister","/#","\n","^Locus: Guten Tag <color=#66DBFF>Magister</color>, wie geht es dir? ","#","^Locus","/#","\n","^Magister: Ach ich komm schon klar. Doch sag mir was führt dich zu mir? Wieder einen Liegestuhl im Schatten für einen Tag oder möchtest du direkt die ganze Woche bestellen? ","#","^Magister","/#","\n","^Locus: Nein diesmal habe ich leider keine Zeit für eine Pause. ","#","^Locus","/#","\n","^Magister: Ach nein? Wieso also besuchst du mich? ","#","^Magister","/#","\n","ev","str","^Feier","/str","/ev",{"*":".^.c-0","flg":20},"ev","str","^Pause","/str","/ev",{"*":".^.c-1","flg":20},"ev","str","^Gehen","/str","/ev",{"*":".^.c-2","flg":20},{"c-0":["^ ",{"->":"Magister.WegenFeier"},"\n",{"#f":5}],"c-1":["^ ",{"->":"Magister.Pause"},"\n",{"#f":5}],"c-2":["^ Locus: Ich wollte nur wissen wie es dir geht. ","#","^Locus","/#","\n","end",{"#f":5}]}],{"#f":1}],"Back":[["^Magister: Willkommen zurück. Jetzt vielleicht eine kleine Pause oder hast du ein anderes Begehr? ","#","^Magister","/#","\n","ev","str","^Feier","/str","/ev",{"*":".^.c-0","flg":20},"ev","str","^Pause","/str",{"CNT?":".^.^.^.Pause"},"!","/ev",{"*":".^.c-1","flg":21},"ev","str","^Gehen","/str","/ev",{"*":".^.c-2","flg":20},{"c-0":["^ ",{"->":"Magister.WegenFeier"},"\n",{"#f":5}],"c-1":["^ ",{"->":"Magister.Pause"},"\n",{"#f":5}],"c-2":["^ Locus: Ich denke ich komme später wieder. ","#","^Locus","/#","\n","end",{"#f":5}]}],{"#f":1}],"Pause":[["^Locus: Ich denke eine Pause im Schatte köntte doch ganz verführerisch sein. Ich nehem einen Liegestuhl bitte! ","#","^Locus","/#","\n","^Magister: Hast du denn auch etwas als Gegenleistung? Du weisst, dass du mir noch zwei Aufenthalte von letzter Woche schuldest. ","#","^Magister","/#","\n","^Locus: Aber sicher doch, ich werde dich nächste Woche bezahlen. Dann bekommst du alles gleichzeitig. Das ist doch am besten für alle. ","#","^Locus","/#","\n","^Magister: Nein, das kann ich nicht zulassen <color=#66DBFF>Locus</color>. Wenn du nicht zahlen kannst bekommst du nichts mehr von mir. Es tut mir leid. ","#","^Magister","/#","\n","^Locus: Schade, aber ich bin sowieso nicht deswegen hier. ","#","^Locus","/#","\n","^Magister: Ach nein? Warum bist du denn gekommen?","\n","ev","str","^Feier","/str","/ev",{"*":".^.c-0","flg":20},"ev","str","^Gehen","/str","/ev",{"*":".^.c-1","flg":20},{"c-0":["^ ",{"->":"Magister.WegenFeier"},"\n",{"#f":5}],"c-1":["^ Locus: Das erzähle ich dir später, ich muss zuerst noch etwas sehr wichtiges erledigen. ","#","^Locus","/#","\n","end",{"#f":5}]}],{"#f":1}],"WegenFeier":[["^Locus: Ich habe einen <color=#58FF5E>Auftrag</color> vom <color=#66DBFF>Meister</color> höchst selbst erhalten. Er wünscht eine <color=#58FF5E>Feier</color> zu seinen Ehren. ","#","^Locus","/#","\n","^Magister: Achja? Wie kommt der <color=#66DBFF>Chef</color> denn dazu dir einen Auftrag zu geben? Hat er deine Qulifikation nicht gelesen? ","#","^Magister","/#","\n","^Locus: Was er sich dabei gedacht hat kann ich dir nicht sagen, ich versuche aber seinen Wünschen nachzukommen. ","#","^Locus","/#","\n","^Magister: Das kann ich verstehen. Was also kann ich tun um dich dabei zu unterstützen? ","#","^Magister","/#","\n","ev","str","^Kuchen","/str","/ev",{"*":".^.c-0","flg":20},"ev","str","^Liegestuhl","/str","/ev",{"*":".^.c-1","flg":20},{"c-0":["^ ",{"->":"Magister.Kuchen"},"\n",{"#f":5}],"c-1":["^ ",{"->":"Magister.Stuhl"},"\n",{"#f":5}]}],{"#f":1}],"Kuchen":[["^Locus: Ich habe nun fast alles zusammen was ich für die <color=#58FF5E>Feier</color> zusammen. Alles was mir noch fehlt ist ein <color=#58FF5E>Kuchen</color>. ","#","^Locus","/#","\n","^Magister: Ein <color=#58FF5E>Kuchen</color>? Und du denkst ich bin ein begnadeter Bäcker oder was?","\n","ev","str","^Ja","/str","/ev",{"*":".^.c-0","flg":20},"ev","str","^Nein","/str","/ev",{"*":".^.c-1","flg":20},{"c-0":[{"->":"Magister.Backen"},"\n",{"#f":5}],"c-1":[{"->":"Magister.NoBacken"},"\n",{"#f":5}]}],{"#f":1}],"Stuhl":["^Locus: Nun um meinen <color=#58FF5E>Auftrag</color> best möglich zu erfüllen benötige ich selbstredend einen eigenen Liegestuhl für.. sagen wir eine Woche. ","#","^Locus","/#","\n","^Magister: Du glaubst doch nicht wirklich, dass ich darauf reinfalle oder? Also was ist jetzt mir deinem Auftrag? ","#","^Magister","/#","\n",{"->":".^.^.Kuchen"},{"#f":1}],"Backen":["^Locus: Als ich <color=#58FF5E>Kuchen</color> hörte warst du der erste der mir in den Sinn gekommen ist! ","#","^Locus","/#","\n","^Magister: Oh wie schön, denn du hast Glück. Ich bin tatsächlich ein begnadeter Bäcker! ","#","^Magister","/#","\n","^Locus: Ok.. Also wirst du mir einen <color=#58FF5E>Kuchen</color> backen? ","#","^Locus","/#","\n",{"->":".^.^.Auftrag"},{"#f":1}],"NoBacken":["^Locus: Selbstverständlich nicht, das wäre ja total merkwürdig aber vielleicht kannst du mir andersweitig helfen. ","#","^Locus","/#","\n","^Magister: Ach.. Wie gemein von dir. Zufällig bin ich ein sehr talentierter Bäcker! Aber das ist also merkwürdig.. Sehr frech! ","#","^Magister","/#","\n","^Locus: So war das gar nicht gemeint. Ich wollte nicht nur nichts zumuten was dich verstimmen könnte. ","#","^Locus","/#","\n","^Magister: Nein nein. Du hast deinen Punkt schon sehr klar gemacht. ","#","^Magister","/#","\n","^Locus: Komm schon, gib mir noch einen Versuch. Ich brauche diesen <color=#58FF5E>Kuchen</color>. ","#","^Locus","/#","\n",{"->":".^.^.Auftrag"},{"#f":1}],"Auftrag":[["^Magister: Gut, ich werde dir einen <color=#58FF5E>Kuchen</color> backen. Aber ich brauche dich für eine <color=#58FF5E>Studie</color> an der ich arbeite. ","#","^Magister","/#","\n","ev","str","^Q-Magister-1","/str",{"x()":"Unity_Event","exArgs":1},"pop","/ev","\n","^Locus: Um was geht es denn in dieser <color=#58FF5E>Studie</color>? ","#","^Locus","/#","\n","^Magister: Es handelt von deiner <color=#58FF5E>Spezies</color>. Ich erforsche die Intelligent verschiedener Vertreter davon. <color=#66DBFF>Rasmus</color> hat mir dabei bereits geholfen. ","#","^Magister","/#","\n","^Magister: Für dich wird es relativ leicht werden. Alles was du tun muss ist mir einige <color=#58FF5E>Fragen</color> zu beantworten und bald hast du deinen <color=#58FF5E>Kuchen</color>. ","#","^Magister","/#","\n","^Magister: Bist du bereit? ","#","^Magister","/#","\n","ev","str","^Ja","/str","/ev",{"*":".^.c-0","flg":20},"ev","str","^Gehen","/str","/ev",{"*":".^.c-1","flg":20},{"c-0":["^ ",{"->":"Magister.Frage1"},"\n",{"#f":5}],"c-1":["^ Locus: Noch nicht, ich werde aber bald wieder kommen. ","#","^Locus","/#","\n","end",{"#f":5}]}],{"#f":1}],"PreBeginn":[["^Magister: ",["ev","visit",2,"MIN","/ev","ev","du",0,"==","/ev",{"->":".^.s0","c":true},"ev","du",1,"==","/ev",{"->":".^.s1","c":true},"ev","du",2,"==","/ev",{"->":".^.s2","c":true},"nop",{"s0":["pop","^Da bist du ja wieder. Bist du nun Bereit?",{"->":".^.^.23"},null],"s1":["pop","^Ganz erhlich so lange geht das Spiel nicht mehr. Also willst du nun beginnen?",{"->":".^.^.23"},null],"s2":["pop","^Können wir jetzt mit der Studie beginnen?",{"->":".^.^.23"},null],"#f":5}],"^ ","#","^Magister","/#","\n","ev","str","^Ja","/str","/ev",{"*":".^.c-0","flg":20},"ev","str","^Gehen","/str","/ev",{"*":".^.c-1","flg":20},{"c-0":["^ ",{"->":"Magister.Frage1"},"\n",{"#f":5}],"c-1":["^ Locus: ",["ev","visit",1,"MIN","/ev","ev","du",0,"==","/ev",{"->":".^.s0","c":true},"ev","du",1,"==","/ev",{"->":".^.s1","c":true},"nop",{"s0":["pop","^Nein, ich brauch noch etwas mehr Zeit.",{"->":".^.^.17"},null],"s1":["pop","^Ich lasse dich wissen wann ich Zeit habe.",{"->":".^.^.17"},null],"#f":5}],"^ ","#","^Locus","/#","\n","end",{"#f":5}]}],{"#f":1}],"Frage1":[["^Locus: Gut, ich bin bereit für die <color=#58FF5E>Fragen</color>. ","#","^Locus","/#","\n","^Magister: Wunderbar. Hier kommt auch schon die erste Frage. ","#","^Magister","/#","\n","^Magister: In meinem Garten sind 10 Pilze. Wenn ich nun alle ausser 4 mitnehmen wie viele Pilze sind dann noch in meinem Garten? ","#","^Magister","/#","\n","ev","str","^0","/str","/ev",{"*":".^.c-0","flg":20},"ev","str","^4","/str","/ev",{"*":".^.c-1","flg":20},"ev","str","^6","/str","/ev",{"*":".^.c-2","flg":20},"ev","str","^10","/str","/ev",{"*":".^.c-3","flg":20},"ev","str","^Apfelsaft","/str",{"CNT?":".^.^.^.Apfelsaft"},"!","/ev",{"*":".^.c-4","flg":21},{"c-0":["^Locus: 0 ","#","^Locus","/#","\n",{"->":"Magister.F1F"},{"#f":5}],"c-1":["^Locus: 4 ","#","^Locus","/#","\n",{"->":"Magister.F1R"},{"#f":5}],"c-2":["^Locus: 6 ","#","^Locus","/#","\n",{"->":"Magister.F1F"},{"#f":5}],"c-3":["^Locus: 10 ","#","^Locus","/#","\n",{"->":"Magister.F1F"},{"#f":5}],"c-4":["^ ",{"->":"Magister.Apfelsaft"},"\n",{"#f":5}]}],{"#f":1}],"F1F":["ev","str","^frage_falsch","/str",1,{"x()":"Add_State","exArgs":2},"pop","/ev","\n","^Magister: Gut, kommen wir zur nächsten Frage. ","#","^Magister","/#","\n",{"->":".^.^.Frage2"},{"#f":1}],"F1R":["ev","str","^frage_richtig","/str",1,{"x()":"Add_State","exArgs":2},"pop","/ev","\n","^Magister: Gut, kommen wir zur nächsten Frage. ","#","^Magister","/#","\n",{"->":".^.^.Frage2"},{"#f":1}],"Apfelsaft":["^Locus: Apfelsaft! ","#","^Locus","/#","\n","^Magister: Apfelsaft? ","#","^Magister","/#","\n","^Locus: Apfelsaft! ","#","^Locus","/#","\n","^Magister: Bitte nimm meine <color=#58FF5E>Fragen</color> ernst. Also machen wir weiter. ","#","^Magister","/#","\n",{"->":".^.^.Frage2"},{"#f":1}],"Frage2":[["^Magister: Du nimmst an einem Rennen teil und du schaffst es den Zweiten zu überholen. An welcher Position bist du nun? ","#","^Magister","/#","\n","ev","str","^Erster","/str","/ev",{"*":".^.c-0","flg":20},"ev","str","^Zweiter","/str","/ev",{"*":".^.c-1","flg":20},"ev","str","^Dritter","/str","/ev",{"*":".^.c-2","flg":20},"ev","str","^Letzter","/str","/ev",{"*":".^.c-3","flg":20},"ev","str","^Geschenkkarten","/str",{"CNT?":".^.^.^.Apfelsaft"},"/ev",{"*":".^.c-4","flg":21},{"c-0":["^Locus: Erster! ","#","^Locus","/#","\n",{"->":"Magister.F2F"},{"#f":5}],"c-1":["^Locus: Zweiter! ","#","^Locus","/#","\n",{"->":"Magister.F2R"},{"#f":5}],"c-2":["^Locus: Dritter! ","#","^Locus","/#","\n",{"->":"Magister.F2F"},{"#f":5}],"c-3":["^Locus: Letzter! ","#","^Locus","/#","\n",{"->":"Magister.F2F"},{"#f":5}],"c-4":[{"->":"Magister.Geschenkkarten"},"\n",{"#f":5}]}],{"#f":1}],"F2F":["ev","str","^frage_falsch","/str",1,{"x()":"Add_State","exArgs":2},"pop","/ev","\n","^Magister: Danke für deine Antwort. Wir fahren fort. ","#","^Magister","/#","\n",{"->":".^.^.Frage3"},{"#f":1}],"F2R":["ev","str","^frage_richtig","/str",1,{"x()":"Add_State","exArgs":2},"pop","/ev","\n","^Magister: Danke für deine Antwort. Wir fahren fort. ","#","^Magister","/#","\n",{"->":".^.^.Frage3"},{"#f":1}],"Geschenkkarten":["ev","str","^frage_falsch","/str",1,{"x()":"Add_State","exArgs":2},"pop","/ev","\n","^Locus: Geschenkkarten! ","#","^Locus","/#","\n","^Magister: Ich sehe schon was das hier wird. <color=#66DBFF>Locus</color>, solltest du meine <color=#58FF5E>Fragen</color> nicht ehrlich beantworten werde ich dir keinen <color=#58FF5E>Kuchen</color> backen und du weisst was dann passiert. ","#","^Magister","/#","\n","^Locus: Nagut, ich werde mich anstrengen. Man darf aber auch gar keinen Spass mehr habe ohne, dass man angeschnauzt wird. ","#","^Locus","/#","\n","^Magister: Du hast es darauf angelegt. Wie auch immer hier kommt die nächste Frage. ","#","^Magister","/#","\n",{"->":".^.^.Frage3"},{"#f":1}],"Frage3":[["^Magister: Wie viele male kann man 10 von 100 subtrahieren? ","#","^Magister","/#","\n","ev","str","^Null","/str","/ev",{"*":".^.c-0","flg":20},"ev","str","^Einmal","/str","/ev",{"*":".^.c-1","flg":20},"ev","str","^Fünf","/str","/ev",{"*":".^.c-2","flg":20},"ev","str","^Zehn","/str","/ev",{"*":".^.c-3","flg":20},{"c-0":["^Locus: Gar nicht, null Mal.","#","^Locus","/#","\n",{"->":"Magister.F3F"},{"#f":5}],"c-1":["^Locus: Einmal! ","#","^Locus","/#","\n",{"->":"Magister.F3R"},{"#f":5}],"c-2":["^Locus: Fünf Mal! ","#","^Locus","/#","\n",{"->":"Magister.F3F"},{"#f":5}],"c-3":["^Locus: Zehn Mal! ","#","^Locus","/#","\n",{"->":"Magister.F3F"},{"#f":5}]}],{"#f":1}],"F3F":["ev","str","^frage_falsch","/str",1,{"x()":"Add_State","exArgs":2},"pop","/ev","\n","^Magister: Wunderbar, wir kommen zur 4. Frage! ","#","^Magister","/#","\n",{"->":".^.^.Frage4"},{"#f":1}],"F3R":["ev","str","^frage_richtig","/str",1,{"x()":"Add_State","exArgs":2},"pop","/ev","\n","^Magister: Wunderbar, wir kommen zur 4. Frage! ","#","^Magister","/#","\n",{"->":".^.^.Frage4"},{"#f":1}],"Frage4":[["^Magister: Als ich 8 Jahre alt war, war meine Schildkröte halb so alt wie ich. Heute bin ich 50 Jahre alt. Wie alt ist meine Schildkröte? ","#","^Magister","/#","\n","ev","str","^8 Jahre","/str","/ev",{"*":".^.c-0","flg":20},"ev","str","^20 Jahre","/str","/ev",{"*":".^.c-1","flg":20},"ev","str","^25 Jahre","/str","/ev",{"*":".^.c-2","flg":20},"ev","str","^46 Jahre","/str","/ev",{"*":".^.c-3","flg":20},{"c-0":["^Locus: 8 Jahre! ","#","^Locus","/#","\n",{"->":"Magister.F4F"},{"#f":5}],"c-1":["^Locus: 20 Jahre! ","#","^Locus","/#","\n",{"->":"Magister.F4F"},{"#f":5}],"c-2":["^Locus: 25 Jahre! ","#","^Locus","/#","\n",{"->":"Magister.F4F"},{"#f":5}],"c-3":["^Locus: 46 Jahre! ","#","^Locus","/#","\n",{"->":"Magister.F4R"},{"#f":5}]}],{"#f":1}],"F4F":["ev","str","^frage_falsch","/str",1,{"x()":"Add_State","exArgs":2},"pop","/ev","\n","^Magister: Wir sind schon fast am Ende. Hier kommt die letzte Frage. ","#","^Magister","/#","\n",{"->":".^.^.Frage5"},{"#f":1}],"F4R":["ev","str","^frage_richtig","/str",1,{"x()":"Add_State","exArgs":2},"pop","/ev","\n","^Magister: Wir sind schon fast am Ende. Hier kommt die letzte Frage. ","#","^Magister","/#","\n",{"->":".^.^.Frage5"},{"#f":1}],"Frage5":[["^Magister: Ein Teich füllt sich mit Seerosen. Jeden Tag verdoppelt sich die Fläche, welche die Seerosen vom Teich einnehmen. Nach 24 Tagen ist der Teich voller Seerosen. Nach wie vielen Tagen war der See halb bedeckt? ","#","^Magister","/#","\n","ev","str","^2 Tage","/str","/ev",{"*":".^.c-0","flg":20},"ev","str","^8 Tage","/str","/ev",{"*":".^.c-1","flg":20},"ev","str","^12 Tage","/str","/ev",{"*":".^.c-2","flg":20},"ev","str","^23 Tage","/str","/ev",{"*":".^.c-3","flg":20},{"c-0":["^Locus: Nach 2 Tagen!","\n",{"->":"Magister.F5F"},{"#f":5}],"c-1":["^Locus: Nach 8 Tagen!","\n",{"->":"Magister.F5F"},{"#f":5}],"c-2":["^Locus: Nach 12 Tagen!","\n",{"->":"Magister.F5F"},{"#f":5}],"c-3":["^Locus: Nach 23 Tagen!","\n",{"->":"Magister.F5R"},{"#f":5}]}],{"#f":1}],"F5F":["ev","str","^frage_falsch","/str",1,{"x()":"Add_State","exArgs":2},"pop","/ev","\n","^Magister: Das waren alle Fragen. Lass mich kurz dein Ergebnis berechnen. ","#","^Magister","/#","\n","^Magister: .","\n","^Magister: ..","\n","^Magister: ...","\n","ev","str","^frage_richtig","/str",{"x()":"Get_State","exArgs":1},4,">","/ev",[{"->":".^.b","c":true},{"b":["^ ",{"->":"Magister.ErgebnisGut"},{"->":".^.^.^.29"},null]}],"nop","\n","ev","str","^frage_falsch","/str",{"x()":"Get_State","exArgs":1},4,">","/ev",[{"->":".^.b","c":true},{"b":["^ ",{"->":"Magister.ErgebnisGut"},{"->":".^.^.^.40"},null]}],"nop","\n",{"->":".^.^.ErgebnisNormal"},{"#f":1}],"F5R":["ev","str","^frage_richtig","/str",1,{"x()":"Add_State","exArgs":2},"pop","/ev","\n","^Magister: Das waren alle Fragen. Lass mich kurz dein Ergebnis berechnen. ","#","^Magister","/#","\n","^Magister: .","\n","^Magister: ..","\n","^Magister: ...","\n","ev","str","^frage_richtig","/str",{"x()":"Get_State","exArgs":1},4,">","/ev",[{"->":".^.b","c":true},{"b":["^ ",{"->":"Magister.ErgebnisGut"},{"->":".^.^.^.29"},null]}],"nop","\n","ev","str","^frage_falsch","/str",{"x()":"Get_State","exArgs":1},4,">","/ev",[{"->":".^.b","c":true},{"b":["^ ",{"->":"Magister.ErgebnisGut"},{"->":".^.^.^.40"},null]}],"nop","\n",{"->":".^.^.ErgebnisNormal"},{"#f":1}],"ErgebnisGut":["^Magister: Herzlichen Glückwunsch, dein Ergebnis ist ungeschlagen! Du hast alles korrekt beantwortet. Deine Leistung übertrifft sogar die von <color=#66DBFF>Rasmus</color>! ","#","^Magister","/#","\n",{"->":".^.^.getKuchen"},{"#f":1}],"ErgebnisNormal":["^Magister: Herzlichen Glückwunsch, dein Ergebnis entspricht dem momentanen Durchschnittswert welcher auch <color=#66DBFF>Rasmus</color> vorgelegt hat. ","#","^Magister","/#","\n",{"->":".^.^.getKuchen"},{"#f":1}],"ErgebnisSchlecht":["^Magister: Herzlichen Glückwunsch, dein Ergebnis ist spektakulär schlecht! Der durchschnittliche Regenwurm hat mehr Grips als du! Nimms aber nicht so schwer, das war ein Beitrag für die Wissenschaft. ","#","^Magister","/#","\n",{"->":".^.^.getKuchen"},{"#f":1}],"getKuchen":["^Locus: Habe ich jetzt etwas gewonnen? ","#","^Locus","/#","\n","^Magister: Ja, wie abgesprochen werde ich dir etwas für deinen <color=#58FF5E>Auftrag</color> backen. ","#","^Magister","/#","\n","^Magister: Ich werde noch einige andere deiner <color=#58FF5E>Spezies</color> befragen müssen um meine Studie zu beenden und ein klares Ergebis zu sehen. ","#","^Magister","/#","\n","^Magister: Ich kümmere mich dann mal um den <color=#58FF5E>Kuchen</color>. Bitte gedulde dich einen Moment. ","#","^Magister","/#","\n","ev","str","^Q-Magister-2","/str",{"x()":"Unity_Event","exArgs":1},"pop","/ev","\n","^Magister: Ich kümmere mich dann mal um den <color=#58FF5E>Kuchen</color>. Bitte gedulde dich einen Moment.","\n","^Magister: Bitte sehr, frisch aus dem Ofen. Ich hoffe er ist ganz nach den höllischen Wünschen unseres <color=#66DBFF>Meister</color>! ","#","^Magister","/#","\n","ev","str","^Q-Magister-3","/str",{"x()":"Unity_Event","exArgs":1},"pop","/ev","\n","ev","str","^item_kuchen","/str",1,{"x()":"Add_State","exArgs":2},"pop","/ev","\n","end",{"#f":1}],"PostMagister":["^Magister: Danke nochmals für die Teilnahme an meiner <color=#58FF5E>Studie</color>. ","#","^Magister","/#","\n","end",{"#f":1}],"#f":1}],"#f":1}],"listDefs":{}}